Workbook

Sheet Partner Directory
A1: Sample Partnership LLC — Partnership Basis Workbook | 2021–2025
A2: Partner Directory & Opening Balances (01/01/2021). Blue = inputs. Green = cross-sheet links. Gold = key figures.
B4: PARTNERSHIP INFORMATION
B5: Partnership Name | C5: Sample Partnership LLC
B6: EIN | C6: XX-XXXXXXX
B7: Tax Year End | C7: December 31
B8: Basis Method | C8: Tax Basis Method (IRC §705 / Rev. Proc. 2020-13)
B9: Filing Form | C9: Form 1065
B10: Periods Covered | C10: 2021 – 2025 (5 rolling years, one tab per year)
B12: PARTNER TABLE — Opening balances = 01/01/2021
B13: # | C13: Partner Name | D13: Entity Type | E13: Opening Tax Basis (2021) | F13: Opening At-Risk (2021) | G13: Opening Recourse Share | H13: Opening Nonrecourse Share | I13: Opening QNRF Share | J13: Opening QNRF Share (§465(b)(6))
B14: 1 | C14: ABC Management LLC | D14: General Partner (GP) | E14: 0 | F14: 0 | G14: 0 | H14: 0 | I14: 0 | J14: 0
B15: 2 | C15: Partner A | D15: Individual | E15: 0 | F15: 0 | G15: 0 | H15: 0 | I15: 0 | J15: 0
B16: 3 | C16: Partner B | D16: Individual | E16: 0 | F16: 0 | G16: 0 | H16: 0 | I16: 0 | J16: 0
B17: 4 | C17: Partner C Trust | D17: Trust | E17: 0 | F17: 0 | G17: 0 | H17: 0 | I17: 0 | J17: 0
B18: 5 | C18: Partner D Trust | D18: Trust | E18: 0 | F18: 0 | G18: 0 | H18: 0 | I18: 0 | J18: 0
B20: ⚠ Opening balances must tie to prior-year K-1s or formation documents. Liability shares = each partner's allocated share (not total).

Sheet 2021
A1: Sample Partnership LLC — Tax Year 2021 (Period 1 of 5)
B2: Blue = inputs. Green = cross-sheet links. Gold = key figures. Update ownership % table (Section A) if interests changed.
B4: SECTION A | OWNERSHIP TABLE — 2021
B5: Nonrecourse liabilities allocated by Profit %. Losses allocated by Loss %. Capital % = economic ownership.
B6: Partner / Metric | C6: ABC Management LLC | D6: Partner A | E6: Partner B | F6: Partner C Trust | G6: Partner D Trust | H6: Check (= 100%?)
B7: Entity Type | C7: General Partner (GP) | D7: Individual | E7: Individual | F7: Trust | G7: Trust
B8: Status | C8: Active | D8: Active | E8: Active | F8: Active | G8: Active
B9: Capital % | C9: 0.2 | D9: 0.2 | E9: 0.2 | F9: 0.2 | G9: 0.2 | H9: =IF(ABS(SUM(C9:G9)-1)<0.0001,TEXT(SUM(C9:G9),"0.0%")&" ✓",TEXT(SUM(C9:G9),"0.0%")&" ⚠") -> 100.0% ✓
B10: Profit % | C10: 0.2 | D10: 0.2 | E10: 0.2 | F10: 0.2 | G10: 0.2 | H10: =IF(ABS(SUM(C10:G10)-1)<0.0001,TEXT(SUM(C10:G10),"0.0%")&" ✓",TEXT(SUM(C10:G10),"0.0%")&" ⚠") -> 100.0% ✓
B11: Loss % | C11: 0.2 | D11: 0.2 | E11: 0.2 | F11: 0.2 | G11: 0.2 | H11: =IF(ABS(SUM(C11:G11)-1)<0.0001,TEXT(SUM(C11:G11),"0.0%")&" ✓",TEXT(SUM(C11:G11),"0.0%")&" ⚠") -> 100.0% ✓
B13: SECTION B | TAX BASIS WORKSHEET — IRC §705 / Rev. Proc. 2020-13 — 2021
B14: K-1 box refs in each label. Lines 4 & 7 auto-linked from Section D. §704(d): losses suspended when decreases exceed basis.
B15: Line Item (K-1 Box Reference) | C15: ABC Management LLC | D15: Partner A | E15: Partner B | F15: Partner C Trust | G15: Partner D Trust | H15: Total
B17: 1. Basis at Beginning of Year | C17: ='Partner Directory'!E14 -> 0 | D17: ='Partner Directory'!E15 -> 0 | E17: ='Partner Directory'!E16 -> 0 | F17: ='Partner Directory'!E17 -> 0 | G17: ='Partner Directory'!E18 -> 0 | H17: =SUM(C17:G17) -> 0
B18: INCREASES (Lines 2–4)
B19: 2a. Cash contributions | C19: 0 | D19: 0 | E19: 0 | F19: 0 | G19: 0 | H19: =SUM(C19:G19) -> 0
B20: 2b. Property contributions (adjusted tax basis, not FMV) | C20: 0 | D20: 0 | E20: 0 | F20: 0 | G20: 0 | H20: =SUM(C20:G20) -> 0
B21: Line 3 — Distributive Share of Income / Gain (K-1)
B22: 3a. Ordinary business income (Box 1) | C22: 0 | D22: 0 | E22: 0 | F22: 0 | G22: 0 | H22: =SUM(C22:G22) -> 0
B23: 3b. Rental real estate / other net rental income (Boxes 2–3) | C23: 0 | D23: 0 | E23: 0 | F23: 0 | G23: 0 | H23: =SUM(C23:G23) -> 0
B24: 3c. Guaranteed payments — services & capital (Boxes 4a, 4b) | C24: 0 | D24: 0 | E24: 0 | F24: 0 | G24: 0 | H24: =SUM(C24:G24) -> 0
B25: 3d. Interest, dividends, royalties (Boxes 5, 6a–6c, 7) | C25: 0 | D25: 0 | E25: 0 | F25: 0 | G25: 0 | H25: =SUM(C25:G25) -> 0
B26: 3e. Net short-term capital gain (Box 8) | C26: 0 | D26: 0 | E26: 0 | F26: 0 | G26: 0 | H26: =SUM(C26:G26) -> 0
B27: 3f. Net long-term / §1250 / collectibles gain (Boxes 9a–9c) | C27: 0 | D27: 0 | E27: 0 | F27: 0 | G27: 0 | H27: =SUM(C27:G27) -> 0
B28: 3g. Net §1231 gain (Box 10) | C28: 0 | D28: 0 | E28: 0 | F28: 0 | G28: 0 | H28: =SUM(C28:G28) -> 0
B29: 3h. Other income & gain (Box 11) | C29: 0 | D29: 0 | E29: 0 | F29: 0 | G29: 0 | H29: =SUM(C29:G29) -> 0
B30: 3i. Tax-exempt income (Box 18, Code A) | C30: 0 | D30: 0 | E30: 0 | F30: 0 | G30: 0 | H30: =SUM(C30:G30) -> 0
B31: 3j. Excess depletion & other increases (Box 20T; other) | C31: 0 | D31: 0 | E31: 0 | F31: 0 | G31: 0 | H31: =SUM(C31:G31) -> 0
B32: Line 3 Total — Income / Gain Subtotal | C32: =SUM(C22:C31) -> 0 | D32: =SUM(D22:D31) -> 0 | E32: =SUM(E22:E31) -> 0 | F32: =SUM(F22:F31) -> 0 | G32: =SUM(G22:G31) -> 0 | H32: =SUM(C32:G32) -> 0
B33: Line 4 — §752 Liability Increase ← auto-linked from Section D
B34: 4. Net increase in share of partnership liabilities (§752) | C34: =MAX(0,C117) -> 0 | D34: =MAX(0,D117) -> 0 | E34: =MAX(0,E117) -> 0 | F34: =MAX(0,F117) -> 0 | G34: =MAX(0,G117) -> 0 | H34: =SUM(C34:G34) -> 0
B35: TOTAL INCREASES (2a + 2b + Line 3 + Line 4) | C35: =C19+C20+C32+C34 -> 0 | D35: =D19+D20+D32+D34 -> 0 | E35: =E19+E20+E32+E34 -> 0 | F35: =F19+F20+F32+F34 -> 0 | G35: =G19+G20+G32+G34 -> 0 | H35: =SUM(C35:G35) -> 0
B36: DECREASES (Lines 5–7)
B37: 5a. Cash distributions (Box 19, Code A) | C37: 0 | D37: 0 | E37: 0 | F37: 0 | G37: 0 | H37: =SUM(C37:G37) -> 0
B38: 5b. Property distributions (adjusted tax basis) (Box 19, Code B) | C38: 0 | D38: 0 | E38: 0 | F38: 0 | G38: 0 | H38: =SUM(C38:G38) -> 0
B39: Line 6 — Distributive Share of Deductions / Losses (K-1)
B40: 6a. Ordinary business loss (Box 1) | C40: 0 | D40: 0 | E40: 0 | F40: 0 | G40: 0 | H40: =SUM(C40:G40) -> 0
B41: 6b. Rental real estate / other net rental loss (Boxes 2–3) | C41: 0 | D41: 0 | E41: 0 | F41: 0 | G41: 0 | H41: =SUM(C41:G41) -> 0
B42: 6c. Net short-term capital loss (Box 8) | C42: 0 | D42: 0 | E42: 0 | F42: 0 | G42: 0 | H42: =SUM(C42:G42) -> 0
B43: 6d. Net long-term capital loss (Box 9a) | C43: 0 | D43: 0 | E43: 0 | F43: 0 | G43: 0 | H43: =SUM(C43:G43) -> 0
B44: 6e. Net §1231 loss (Box 10) | C44: 0 | D44: 0 | E44: 0 | F44: 0 | G44: 0 | H44: =SUM(C44:G44) -> 0
B45: 6f. Section 179 deduction (Box 12) | C45: 0 | D45: 0 | E45: 0 | F45: 0 | G45: 0 | H45: =SUM(C45:G45) -> 0
B46: 6g. Charitable contributions (Box 13A) | C46: 0 | D46: 0 | E46: 0 | F46: 0 | G46: 0 | H46: =SUM(C46:G46) -> 0
B47: 6h. Investment interest / §59(e)(2) / excess biz interest (Box 13 B/C/K) | C47: 0 | D47: 0 | E47: 0 | F47: 0 | G47: 0 | H47: =SUM(C47:G47) -> 0
B48: 6i. Foreign taxes paid or accrued (Box 13L) | C48: 0 | D48: 0 | E48: 0 | F48: 0 | G48: 0 | H48: =SUM(C48:G48) -> 0
B49: 6j. Nondeductible / non-capitalizable expenses (Box 18C) | C49: 0 | D49: 0 | E49: 0 | F49: 0 | G49: 0 | H49: =SUM(C49:G49) -> 0
B50: 6k. Other losses & deductions (Box 11 / Box 13W / Box 20T; other) | C50: 0 | D50: 0 | E50: 0 | F50: 0 | G50: 0 | H50: =SUM(C50:G50) -> 0
B51: Line 6 Total — Deductions / Losses Subtotal | C51: =SUM(C40:C50) -> 0 | D51: =SUM(D40:D50) -> 0 | E51: =SUM(E40:E50) -> 0 | F51: =SUM(F40:F50) -> 0 | G51: =SUM(G40:G50) -> 0 | H51: =SUM(C51:G51) -> 0
B52: Line 7 — §752 Liability Decrease ← auto-linked from Section D
B53: 7. Net decrease in share of partnership liabilities (§752) | C53: =MAX(0,-C117) -> 0 | D53: =MAX(0,-D117) -> 0 | E53: =MAX(0,-E117) -> 0 | F53: =MAX(0,-F117) -> 0 | G53: =MAX(0,-G117) -> 0 | H53: =SUM(C53:G53) -> 0
B54: TOTAL DECREASES (5a + 5b + Line 6 + Line 7) | C54: =C37+C38+C51+C53 -> 0 | D54: =D37+D38+D51+D53 -> 0 | E54: =E37+E38+E51+E53 -> 0 | F54: =F37+F38+F51+F53 -> 0 | G54: =G37+G38+G51+G53 -> 0 | H54: =SUM(C54:G54) -> 0
B55: §704(d) LOSS LIMITATION
B56: 8. Pre-Limitation Adjusted Basis (Line 1 + Increases − Decreases) | C56: =C17+C35-C54 -> 0 | D56: =D17+D35-D54 -> 0 | E56: =E17+E35-E54 -> 0 | F56: =F17+F35-F54 -> 0 | G56: =G17+G35-G54 -> 0 | H56: =SUM(C56:G56) -> 0
B57: 9a. §704(d) Suspended Losses [excess of decreases over available basis] | C57: =MAX(0,-C56) -> 0 | D57: =MAX(0,-D56) -> 0 | E57: =MAX(0,-E56) -> 0 | F57: =MAX(0,-F56) -> 0 | G57: =MAX(0,-G56) -> 0 | H57: =SUM(C57:G57) -> 0
B58: 9b. Prior-Year §704(d) Suspended Losses Restored / Utilized (enter as positive) | C58: 0 | D58: 0 | E58: 0 | F58: 0 | G58: 0 | H58: =SUM(C58:G58) -> 0
B59: 10. Ending Tax Basis — December 31, 2021 | C59: =MAX(0,C56)-C58 -> 0 | D59: =MAX(0,D56)-D58 -> 0 | E59: =MAX(0,E56)-E58 -> 0 | F59: =MAX(0,F56)-F58 -> 0 | G59: =MAX(0,G56)-G58 -> 0 | H59: =SUM(C59:G59) -> 0
B61: SECTION C | AT-RISK BASIS — IRC §465 — 2021
B62: At-risk = cash/property + recourse debt + QNRF. Nonrecourse does NOT increase at-risk. §465 applied after §704(d).
B63: Line Item | C63: ABC Management LLC | D63: Partner A | E63: Partner B | F63: Partner C Trust | G63: Partner D Trust | H63: Total
B65: 1. At-Risk Amount at Beginning of Year | C65: ='Partner Directory'!F14 -> 0 | D65: ='Partner Directory'!F15 -> 0 | E65: ='Partner Directory'!F16 -> 0 | F65: ='Partner Directory'!F17 -> 0 | G65: ='Partner Directory'!F18 -> 0 | H65: =SUM(C65:G65) -> 0
B66: INCREASES
B67: 2a. Cash contributions ← Section B Line 2a | C67: =C19 -> 0 | D67: =D19 -> 0 | E67: =E19 -> 0 | F67: =F19 -> 0 | G67: =G19 -> 0 | H67: =SUM(C67:G67) -> 0
B68: 2b. Property contributions ← Section B Line 2b | C68: =C20 -> 0 | D68: =D20 -> 0 | E68: =E20 -> 0 | F68: =F20 -> 0 | G68: =G20 -> 0 | H68: =SUM(C68:G68) -> 0
B69: 2c. Recourse borrowings ← Section D Recourse increases | C69: =C96 -> 0 | D69: =D96 -> 0 | E69: =E96 -> 0 | F69: =F96 -> 0 | G69: =G96 -> 0 | H69: =SUM(C69:G69) -> 0
B70: 2d. QNRF increase ← Section D | C70: =MAX(0,C112-'Partner Directory'!J14) -> 0 | D70: =MAX(0,D112-'Partner Directory'!J15) -> 0 | E70: =MAX(0,E112-'Partner Directory'!J16) -> 0 | F70: =MAX(0,F112-'Partner Directory'!J17) -> 0 | G70: =MAX(0,G112-'Partner Directory'!J18) -> 0 | H70: =SUM(C70:G70) -> 0
B71: 2e. Distributive share of income/gain ← Section B Line 3 | C71: =C32 -> 0 | D71: =D32 -> 0 | E71: =E32 -> 0 | F71: =F32 -> 0 | G71: =G32 -> 0 | H71: =SUM(C71:G71) -> 0
B72: 2f. Other increases to at-risk amount | C72: 0 | D72: 0 | E72: 0 | F72: 0 | G72: 0 | H72: =SUM(C72:G72) -> 0
B73: TOTAL INCREASES | C73: =C67+C68+C69+C70+C71+C72 -> 0 | D73: =D67+D68+D69+D70+D71+D72 -> 0 | E73: =E67+E68+E69+E70+E71+E72 -> 0 | F73: =F67+F68+F69+F70+F71+F72 -> 0 | G73: =G67+G68+G69+G70+G71+G72 -> 0 | H73: =SUM(C73:G73) -> 0
B74: DECREASES
B75: 3a. Cash distributions ← Section B Line 5a | C75: =C37 -> 0 | D75: =D37 -> 0 | E75: =E37 -> 0 | F75: =F37 -> 0 | G75: =G37 -> 0 | H75: =SUM(C75:G75) -> 0
B76: 3b. Property distributions ← Section B Line 5b | C76: =C38 -> 0 | D76: =D38 -> 0 | E76: =E38 -> 0 | F76: =F38 -> 0 | G76: =G38 -> 0 | H76: =SUM(C76:G76) -> 0
B77: 3c. Recourse repayments ← Section D Recourse decreases | C77: =C97 -> 0 | D77: =D97 -> 0 | E77: =E97 -> 0 | F77: =F97 -> 0 | G77: =G97 -> 0 | H77: =SUM(C77:G77) -> 0
B78: 3d. QNRF decrease ← Section D | C78: =MAX(0,'Partner Directory'!J14-C112) -> 0 | D78: =MAX(0,'Partner Directory'!J15-D112) -> 0 | E78: =MAX(0,'Partner Directory'!J16-E112) -> 0 | F78: =MAX(0,'Partner Directory'!J17-F112) -> 0 | G78: =MAX(0,'Partner Directory'!J18-G112) -> 0 | H78: =SUM(C78:G78) -> 0
B79: 3e. Distributive share of deductions/losses ← Section B Line 6 | C79: =C51 -> 0 | D79: =D51 -> 0 | E79: =E51 -> 0 | F79: =F51 -> 0 | G79: =G51 -> 0 | H79: =SUM(C79:G79) -> 0
B80: 3f. Other decreases to at-risk amount | C80: 0 | D80: 0 | E80: 0 | F80: 0 | G80: 0 | H80: =SUM(C80:G80) -> 0
B81: TOTAL DECREASES | C81: =C75+C76+C77+C78+C79+C80 -> 0 | D81: =D75+D76+D77+D78+D79+D80 -> 0 | E81: =E75+E76+E77+E78+E79+E80 -> 0 | F81: =F75+F76+F77+F78+F79+F80 -> 0 | G81: =G75+G76+G77+G78+G79+G80 -> 0 | H81: =SUM(C81:G81) -> 0
B82: 4. Pre-Limitation At-Risk Amount | C82: =C65+C73-C81 -> 0 | D82: =D65+D73-D81 -> 0 | E82: =E65+E73-E81 -> 0 | F82: =F65+F73-F81 -> 0 | G82: =G65+G73-G81 -> 0 | H82: =SUM(C82:G82) -> 0
B83: §465 LOSS LIMITATION
B84: 5a. §465 Suspended Losses | C84: =MAX(0,-C82) -> 0 | D84: =MAX(0,-D82) -> 0 | E84: =MAX(0,-E82) -> 0 | F84: =MAX(0,-F82) -> 0 | G84: =MAX(0,-G82) -> 0 | H84: =SUM(C84:G84) -> 0
B85: 5b. Prior-Year §465 Suspended Losses Restored (enter as positive) | C85: 0 | D85: 0 | E85: 0 | F85: 0 | G85: 0 | H85: =SUM(C85:G85) -> 0
B86: 6. Ending At-Risk Amount — December 31, 2021 | C86: =MAX(0,C82)-C85 -> 0 | D86: =MAX(0,D82)-D85 -> 0 | E86: =MAX(0,E82)-E85 -> 0 | F86: =MAX(0,F82)-F85 -> 0 | G86: =MAX(0,G82)-G85 -> 0 | H86: =SUM(C86:G86) -> 0
B87: 7. Effective Loss Limit (lesser of Tax Basis & At-Risk) | C87: =MIN(C59,C86) -> 0 | D87: =MIN(D59,D86) -> 0 | E87: =MIN(E59,E86) -> 0 | F87: =MIN(F59,F86) -> 0 | G87: =MIN(G59,G86) -> 0 | H87: =SUM(C87:G87) -> 0
B89: SECTION D | LIABILITY SCHEDULE — IRC §752 — 2021
B90: Recourse §1.752-2: economic risk of loss. Nonrecourse §1.752-3: allocated by Profit %. QNRF §465(b)(6): real property.
B91: Item | C91: ABC Management LLC | D91: Partner A | E91: Partner B | F91: Partner C Trust | G91: Partner D Trust | H91: Total / Sum Check
B93: RECOURSE (§1.752-2 — Economic Risk of Loss)
B94: Total Partnership Amount (enter full liability) | C94: 0 | D94: (partner shares entered below)
B95: Beginning of Year — Each Partner's Share | C95: ='Partner Directory'!H14 -> 0 | D95: ='Partner Directory'!H15 -> 0 | E95: ='Partner Directory'!H16 -> 0 | F95: ='Partner Directory'!H17 -> 0 | G95: ='Partner Directory'!H18 -> 0 | H95: =SUM(C95:G95) -> 0
B96: Increases in Share During Year | C96: 0 | D96: 0 | E96: 0 | F96: 0 | G96: 0 | H96: =SUM(C96:G96) -> 0
B97: Decreases in Share During Year | C97: 0 | D97: 0 | E97: 0 | F97: 0 | G97: 0 | H97: =SUM(C97:G97) -> 0
B98: End of Year — Each Partner's Share | C98: =C95+C96-C97 -> 0 | D98: =D95+D96-D97 -> 0 | E98: =E95+E96-E97 -> 0 | F98: =F95+F96-F97 -> 0 | G98: =G95+G96-G97 -> 0 | H98: =IF(ABS(C94-SUM(C98:G98))<1,TEXT(SUM(C98:G98),"$#,##0")&" ✓",TEXT(SUM(C98:G98),"$#,##0")&" ⚠ gap") -> $0 ✓
B100: NONRECOURSE (§1.752-3 — allocated by Profit %)
B101: Total Partnership Amount (enter full liability) | C101: 0 | D101: (partner shares entered below)
B102: Beginning of Year — Each Partner's Share | C102: ='Partner Directory'!I14 -> 0 | D102: ='Partner Directory'!I15 -> 0 | E102: ='Partner Directory'!I16 -> 0 | F102: ='Partner Directory'!I17 -> 0 | G102: ='Partner Directory'!I18 -> 0 | H102: =SUM(C102:G102) -> 0
B103: Increases in Share During Year | C103: 0 | D103: 0 | E103: 0 | F103: 0 | G103: 0 | H103: =SUM(C103:G103) -> 0
B104: Decreases in Share During Year | C104: 0 | D104: 0 | E104: 0 | F104: 0 | G104: 0 | H104: =SUM(C104:G104) -> 0
B105: End of Year — Each Partner's Share | C105: =C102+C103-C104 -> 0 | D105: =D102+D103-D104 -> 0 | E105: =E102+E103-E104 -> 0 | F105: =F102+F103-F104 -> 0 | G105: =G102+G103-G104 -> 0 | H105: =IF(ABS(C101-SUM(C105:G105))<1,TEXT(SUM(C105:G105),"$#,##0")&" ✓",TEXT(SUM(C105:G105),"$#,##0")&" ⚠ gap") -> $0 ✓
B107: QNRF (§465(b)(6) — Qualified Nonrecourse Financing)
B108: Total Partnership Amount (enter full liability) | C108: 0 | D108: (partner shares entered below)
B109: Beginning of Year — Each Partner's Share | C109: ='Partner Directory'!J14 -> 0 | D109: ='Partner Directory'!J15 -> 0 | E109: ='Partner Directory'!J16 -> 0 | F109: ='Partner Directory'!J17 -> 0 | G109: ='Partner Directory'!J18 -> 0 | H109: =SUM(C109:G109) -> 0
...

Sheet 2022
A1: Sample Partnership LLC — Tax Year 2022 (Period 2 of 5)
B2: Blue = inputs. Green = cross-sheet links. Gold = key figures. Update ownership % table (Section A) if interests changed.
B4: SECTION A | OWNERSHIP TABLE — 2022
B5: Nonrecourse liabilities allocated by Profit %. Losses allocated by Loss %. Capital % = economic ownership.
B6: Partner / Metric | C6: ABC Management LLC | D6: Partner A | E6: Partner B | F6: Partner C Trust | G6: Partner D Trust | H6: Check (= 100%?)
B7: Entity Type | C7: General Partner (GP) | D7: Individual | E7: Individual | F7: Trust | G7: Trust
B8: Status | C8: Active | D8: Active | E8: Active | F8: Active | G8: Active
B9: Capital % | C9: 0.2 | D9: 0.2 | E9: 0.2 | F9: 0.2 | G9: 0.2 | H9: =IF(ABS(SUM(C9:G9)-1)<0.0001,TEXT(SUM(C9:G9),"0.0%")&" ✓",TEXT(SUM(C9:G9),"0.0%")&" ⚠") -> 100.0% ✓
B10: Profit % | C10: 0.2 | D10: 0.2 | E10: 0.2 | F10: 0.2 | G10: 0.2 | H10: =IF(ABS(SUM(C10:G10)-1)<0.0001,TEXT(SUM(C10:G10),"0.0%")&" ✓",TEXT(SUM(C10:G10),"0.0%")&" ⚠") -> 100.0% ✓
B11: Loss % | C11: 0.2 | D11: 0.2 | E11: 0.2 | F11: 0.2 | G11: 0.2 | H11: =IF(ABS(SUM(C11:G11)-1)<0.0001,TEXT(SUM(C11:G11),"0.0%")&" ✓",TEXT(SUM(C11:G11),"0.0%")&" ⚠") -> 100.0% ✓
B13: SECTION B | TAX BASIS WORKSHEET — IRC §705 / Rev. Proc. 2020-13 — 2022
B14: K-1 box refs in each label. Lines 4 & 7 auto-linked from Section D. §704(d): losses suspended when decreases exceed basis.
B15: Line Item (K-1 Box Reference) | C15: ABC Management LLC | D15: Partner A | E15: Partner B | F15: Partner C Trust | G15: Partner D Trust | H15: Total
B17: 1. Basis at Beginning of Year | C17: ='2021'!C59 -> 0 | D17: ='2021'!D59 -> 0 | E17: ='2021'!E59 -> 0 | F17: ='2021'!F59 -> 0 | G17: ='2021'!G59 -> 0 | H17: =SUM(C17:G17) -> 0
B18: INCREASES (Lines 2–4)
B19: 2a. Cash contributions | C19: 0 | D19: 0 | E19: 0 | F19: 0 | G19: 0 | H19: =SUM(C19:G19) -> 0
B20: 2b. Property contributions (adjusted tax basis, not FMV) | C20: 0 | D20: 0 | E20: 0 | F20: 0 | G20: 0 | H20: =SUM(C20:G20) -> 0
B21: Line 3 — Distributive Share of Income / Gain (K-1)
B22: 3a. Ordinary business income (Box 1) | C22: 0 | D22: 0 | E22: 0 | F22: 0 | G22: 0 | H22: =SUM(C22:G22) -> 0
B23: 3b. Rental real estate / other net rental income (Boxes 2–3) | C23: 0 | D23: 0 | E23: 0 | F23: 0 | G23: 0 | H23: =SUM(C23:G23) -> 0
B24: 3c. Guaranteed payments — services & capital (Boxes 4a, 4b) | C24: 0 | D24: 0 | E24: 0 | F24: 0 | G24: 0 | H24: =SUM(C24:G24) -> 0
B25: 3d. Interest, dividends, royalties (Boxes 5, 6a–6c, 7) | C25: 0 | D25: 0 | E25: 0 | F25: 0 | G25: 0 | H25: =SUM(C25:G25) -> 0
B26: 3e. Net short-term capital gain (Box 8) | C26: 0 | D26: 0 | E26: 0 | F26: 0 | G26: 0 | H26: =SUM(C26:G26) -> 0
B27: 3f. Net long-term / §1250 / collectibles gain (Boxes 9a–9c) | C27: 0 | D27: 0 | E27: 0 | F27: 0 | G27: 0 | H27: =SUM(C27:G27) -> 0
B28: 3g. Net §1231 gain (Box 10) | C28: 0 | D28: 0 | E28: 0 | F28: 0 | G28: 0 | H28: =SUM(C28:G28) -> 0
B29: 3h. Other income & gain (Box 11) | C29: 0 | D29: 0 | E29: 0 | F29: 0 | G29: 0 | H29: =SUM(C29:G29) -> 0
B30: 3i. Tax-exempt income (Box 18, Code A) | C30: 0 | D30: 0 | E30: 0 | F30: 0 | G30: 0 | H30: =SUM(C30:G30) -> 0
B31: 3j. Excess depletion & other increases (Box 20T; other) | C31: 0 | D31: 0 | E31: 0 | F31: 0 | G31: 0 | H31: =SUM(C31:G31) -> 0
B32: Line 3 Total — Income / Gain Subtotal | C32: =SUM(C22:C31) -> 0 | D32: =SUM(D22:D31) -> 0 | E32: =SUM(E22:E31) -> 0 | F32: =SUM(F22:F31) -> 0 | G32: =SUM(G22:G31) -> 0 | H32: =SUM(C32:G32) -> 0
B33: Line 4 — §752 Liability Increase ← auto-linked from Section D
B34: 4. Net increase in share of partnership liabilities (§752) | C34: =MAX(0,C117) -> 0 | D34: =MAX(0,D117) -> 0 | E34: =MAX(0,E117) -> 0 | F34: =MAX(0,F117) -> 0 | G34: =MAX(0,G117) -> 0 | H34: =SUM(C34:G34) -> 0
B35: TOTAL INCREASES (2a + 2b + Line 3 + Line 4) | C35: =C19+C20+C32+C34 -> 0 | D35: =D19+D20+D32+D34 -> 0 | E35: =E19+E20+E32+E34 -> 0 | F35: =F19+F20+F32+F34 -> 0 | G35: =G19+G20+G32+G34 -> 0 | H35: =SUM(C35:G35) -> 0
B36: DECREASES (Lines 5–7)
B37: 5a. Cash distributions (Box 19, Code A) | C37: 0 | D37: 0 | E37: 0 | F37: 0 | G37: 0 | H37: =SUM(C37:G37) -> 0
B38: 5b. Property distributions (adjusted tax basis) (Box 19, Code B) | C38: 0 | D38: 0 | E38: 0 | F38: 0 | G38: 0 | H38: =SUM(C38:G38) -> 0
B39: Line 6 — Distributive Share of Deductions / Losses (K-1)
B40: 6a. Ordinary business loss (Box 1) | C40: 0 | D40: 0 | E40: 0 | F40: 0 | G40: 0 | H40: =SUM(C40:G40) -> 0
B41: 6b. Rental real estate / other net rental loss (Boxes 2–3) | C41: 0 | D41: 0 | E41: 0 | F41: 0 | G41: 0 | H41: =SUM(C41:G41) -> 0
B42: 6c. Net short-term capital loss (Box 8) | C42: 0 | D42: 0 | E42: 0 | F42: 0 | G42: 0 | H42: =SUM(C42:G42) -> 0
B43: 6d. Net long-term capital loss (Box 9a) | C43: 0 | D43: 0 | E43: 0 | F43: 0 | G43: 0 | H43: =SUM(C43:G43) -> 0
B44: 6e. Net §1231 loss (Box 10) | C44: 0 | D44: 0 | E44: 0 | F44: 0 | G44: 0 | H44: =SUM(C44:G44) -> 0
B45: 6f. Section 179 deduction (Box 12) | C45: 0 | D45: 0 | E45: 0 | F45: 0 | G45: 0 | H45: =SUM(C45:G45) -> 0
B46: 6g. Charitable contributions (Box 13A) | C46: 0 | D46: 0 | E46: 0 | F46: 0 | G46: 0 | H46: =SUM(C46:G46) -> 0
B47: 6h. Investment interest / §59(e)(2) / excess biz interest (Box 13 B/C/K) | C47: 0 | D47: 0 | E47: 0 | F47: 0 | G47: 0 | H47: =SUM(C47:G47) -> 0
B48: 6i. Foreign taxes paid or accrued (Box 13L) | C48: 0 | D48: 0 | E48: 0 | F48: 0 | G48: 0 | H48: =SUM(C48:G48) -> 0
B49: 6j. Nondeductible / non-capitalizable expenses (Box 18C) | C49: 0 | D49: 0 | E49: 0 | F49: 0 | G49: 0 | H49: =SUM(C49:G49) -> 0
B50: 6k. Other losses & deductions (Box 11 / Box 13W / Box 20T; other) | C50: 0 | D50: 0 | E50: 0 | F50: 0 | G50: 0 | H50: =SUM(C50:G50) -> 0
B51: Line 6 Total — Deductions / Losses Subtotal | C51: =SUM(C40:C50) -> 0 | D51: =SUM(D40:D50) -> 0 | E51: =SUM(E40:E50) -> 0 | F51: =SUM(F40:F50) -> 0 | G51: =SUM(G40:G50) -> 0 | H51: =SUM(C51:G51) -> 0
B52: Line 7 — §752 Liability Decrease ← auto-linked from Section D
B53: 7. Net decrease in share of partnership liabilities (§752) | C53: =MAX(0,-C117) -> 0 | D53: =MAX(0,-D117) -> 0 | E53: =MAX(0,-E117) -> 0 | F53: =MAX(0,-F117) -> 0 | G53: =MAX(0,-G117) -> 0 | H53: =SUM(C53:G53) -> 0
B54: TOTAL DECREASES (5a + 5b + Line 6 + Line 7) | C54: =C37+C38+C51+C53 -> 0 | D54: =D37+D38+D51+D53 -> 0 | E54: =E37+E38+E51+E53 -> 0 | F54: =F37+F38+F51+F53 -> 0 | G54: =G37+G38+G51+G53 -> 0 | H54: =SUM(C54:G54) -> 0
B55: §704(d) LOSS LIMITATION
B56: 8. Pre-Limitation Adjusted Basis (Line 1 + Increases − Decreases) | C56: =C17+C35-C54 -> 0 | D56: =D17+D35-D54 -> 0 | E56: =E17+E35-E54 -> 0 | F56: =F17+F35-F54 -> 0 | G56: =G17+G35-G54 -> 0 | H56: =SUM(C56:G56) -> 0
B57: 9a. §704(d) Suspended Losses [excess of decreases over available basis] | C57: =MAX(0,-C56) -> 0 | D57: =MAX(0,-D56) -> 0 | E57: =MAX(0,-E56) -> 0 | F57: =MAX(0,-F56) -> 0 | G57: =MAX(0,-G56) -> 0 | H57: =SUM(C57:G57) -> 0
B58: 9b. Prior-Year §704(d) Suspended Losses Restored ← auto from 2021 | C58: =MIN('2021'!C57,MAX(0,C56)) -> 0 | D58: =MIN('2021'!D57,MAX(0,D56)) -> 0 | E58: =MIN('2021'!E57,MAX(0,E56)) -> 0 | F58: =MIN('2021'!F57,MAX(0,F56)) -> 0 | G58: =MIN('2021'!G57,MAX(0,G56)) -> 0 | H58: =SUM(C58:G58) -> 0
B59: 10. Ending Tax Basis — December 31, 2022 | C59: =MAX(0,C56)-C58 -> 0 | D59: =MAX(0,D56)-D58 -> 0 | E59: =MAX(0,E56)-E58 -> 0 | F59: =MAX(0,F56)-F58 -> 0 | G59: =MAX(0,G56)-G58 -> 0 | H59: =SUM(C59:G59) -> 0
B61: SECTION C | AT-RISK BASIS — IRC §465 — 2022
B62: At-risk = cash/property + recourse debt + QNRF. Nonrecourse does NOT increase at-risk. §465 applied after §704(d).
B63: Line Item | C63: ABC Management LLC | D63: Partner A | E63: Partner B | F63: Partner C Trust | G63: Partner D Trust | H63: Total
B65: 1. At-Risk Amount at Beginning of Year | C65: ='2021'!C86 -> 0 | D65: ='2021'!D86 -> 0 | E65: ='2021'!E86 -> 0 | F65: ='2021'!F86 -> 0 | G65: ='2021'!G86 -> 0 | H65: =SUM(C65:G65) -> 0
B66: INCREASES
B67: 2a. Cash contributions ← Section B Line 2a | C67: =C19 -> 0 | D67: =D19 -> 0 | E67: =E19 -> 0 | F67: =F19 -> 0 | G67: =G19 -> 0 | H67: =SUM(C67:G67) -> 0
B68: 2b. Property contributions ← Section B Line 2b | C68: =C20 -> 0 | D68: =D20 -> 0 | E68: =E20 -> 0 | F68: =F20 -> 0 | G68: =G20 -> 0 | H68: =SUM(C68:G68) -> 0
B69: 2c. Recourse borrowings ← Section D Recourse increases | C69: =C96 -> 0 | D69: =D96 -> 0 | E69: =E96 -> 0 | F69: =F96 -> 0 | G69: =G96 -> 0 | H69: =SUM(C69:G69) -> 0
B70: 2d. QNRF increase ← Section D | C70: =MAX(0,C112-'2021'!C112) -> 0 | D70: =MAX(0,D112-'2021'!D112) -> 0 | E70: =MAX(0,E112-'2021'!E112) -> 0 | F70: =MAX(0,F112-'2021'!F112) -> 0 | G70: =MAX(0,G112-'2021'!G112) -> 0 | H70: =SUM(C70:G70) -> 0
B71: 2e. Distributive share of income/gain ← Section B Line 3 | C71: =C32 -> 0 | D71: =D32 -> 0 | E71: =E32 -> 0 | F71: =F32 -> 0 | G71: =G32 -> 0 | H71: =SUM(C71:G71) -> 0
B72: 2f. Other increases to at-risk amount | C72: 0 | D72: 0 | E72: 0 | F72: 0 | G72: 0 | H72: =SUM(C72:G72) -> 0
B73: TOTAL INCREASES | C73: =C67+C68+C69+C70+C71+C72 -> 0 | D73: =D67+D68+D69+D70+D71+D72 -> 0 | E73: =E67+E68+E69+E70+E71+E72 -> 0 | F73: =F67+F68+F69+F70+F71+F72 -> 0 | G73: =G67+G68+G69+G70+G71+G72 -> 0 | H73: =SUM(C73:G73) -> 0
B74: DECREASES
B75: 3a. Cash distributions ← Section B Line 5a | C75: =C37 -> 0 | D75: =D37 -> 0 | E75: =E37 -> 0 | F75: =F37 -> 0 | G75: =G37 -> 0 | H75: =SUM(C75:G75) -> 0
B76: 3b. Property distributions ← Section B Line 5b | C76: =C38 -> 0 | D76: =D38 -> 0 | E76: =E38 -> 0 | F76: =F38 -> 0 | G76: =G38 -> 0 | H76: =SUM(C76:G76) -> 0
B77: 3c. Recourse repayments ← Section D Recourse decreases | C77: =C97 -> 0 | D77: =D97 -> 0 | E77: =E97 -> 0 | F77: =F97 -> 0 | G77: =G97 -> 0 | H77: =SUM(C77:G77) -> 0
B78: 3d. QNRF decrease ← Section D | C78: =MAX(0,'2021'!C112-C112) -> 0 | D78: =MAX(0,'2021'!D112-D112) -> 0 | E78: =MAX(0,'2021'!E112-E112) -> 0 | F78: =MAX(0,'2021'!F112-F112) -> 0 | G78: =MAX(0,'2021'!G112-G112) -> 0 | H78: =SUM(C78:G78) -> 0
B79: 3e. Distributive share of deductions/losses ← Section B Line 6 | C79: =C51 -> 0 | D79: =D51 -> 0 | E79: =E51 -> 0 | F79: =F51 -> 0 | G79: =G51 -> 0 | H79: =SUM(C79:G79) -> 0
B80: 3f. Other decreases to at-risk amount | C80: 0 | D80: 0 | E80: 0 | F80: 0 | G80: 0 | H80: =SUM(C80:G80) -> 0
B81: TOTAL DECREASES | C81: =C75+C76+C77+C78+C79+C80 -> 0 | D81: =D75+D76+D77+D78+D79+D80 -> 0 | E81: =E75+E76+E77+E78+E79+E80 -> 0 | F81: =F75+F76+F77+F78+F79+F80 -> 0 | G81: =G75+G76+G77+G78+G79+G80 -> 0 | H81: =SUM(C81:G81) -> 0
B82: 4. Pre-Limitation At-Risk Amount | C82: =C65+C73-C81 -> 0 | D82: =D65+D73-D81 -> 0 | E82: =E65+E73-E81 -> 0 | F82: =F65+F73-F81 -> 0 | G82: =G65+G73-G81 -> 0 | H82: =SUM(C82:G82) -> 0
B83: §465 LOSS LIMITATION
B84: 5a. §465 Suspended Losses | C84: =MAX(0,-C82) -> 0 | D84: =MAX(0,-D82) -> 0 | E84: =MAX(0,-E82) -> 0 | F84: =MAX(0,-F82) -> 0 | G84: =MAX(0,-G82) -> 0 | H84: =SUM(C84:G84) -> 0
B85: 5b. Prior-Year §465 Suspended Losses Restored ← auto from 2021 | C85: =MIN('2021'!C84,MAX(0,C82)) -> 0 | D85: =MIN('2021'!D84,MAX(0,D82)) -> 0 | E85: =MIN('2021'!E84,MAX(0,E82)) -> 0 | F85: =MIN('2021'!F84,MAX(0,F82)) -> 0 | G85: =MIN('2021'!G84,MAX(0,G82)) -> 0 | H85: =SUM(C85:G85) -> 0
B86: 6. Ending At-Risk Amount — December 31, 2022 | C86: =MAX(0,C82)-C85 -> 0 | D86: =MAX(0,D82)-D85 -> 0 | E86: =MAX(0,E82)-E85 -> 0 | F86: =MAX(0,F82)-F85 -> 0 | G86: =MAX(0,G82)-G85 -> 0 | H86: =SUM(C86:G86) -> 0
B87: 7. Effective Loss Limit (lesser of Tax Basis & At-Risk) | C87: =MIN(C59,C86) -> 0 | D87: =MIN(D59,D86) -> 0 | E87: =MIN(E59,E86) -> 0 | F87: =MIN(F59,F86) -> 0 | G87: =MIN(G59,G86) -> 0 | H87: =SUM(C87:G87) -> 0
B89: SECTION D | LIABILITY SCHEDULE — IRC §752 — 2022
B90: Recourse §1.752-2: economic risk of loss. Nonrecourse §1.752-3: allocated by Profit %. QNRF §465(b)(6): real property.
B91: Item | C91: ABC Management LLC | D91: Partner A | E91: Partner B | F91: Partner C Trust | G91: Partner D Trust | H91: Total / Sum Check
B93: RECOURSE (§1.752-2 — Economic Risk of Loss)
B94: Total Partnership Amount (enter full liability) | C94: 0 | D94: (partner shares entered below)
B95: Beginning of Year — Each Partner's Share | C95: ='2021'!C98 -> 0 | D95: ='2021'!D98 -> 0 | E95: ='2021'!E98 -> 0 | F95: ='2021'!F98 -> 0 | G95: ='2021'!G98 -> 0 | H95: =SUM(C95:G95) -> 0
B96: Increases in Share During Year | C96: 0 | D96: 0 | E96: 0 | F96: 0 | G96: 0 | H96: =SUM(C96:G96) -> 0
B97: Decreases in Share During Year | C97: 0 | D97: 0 | E97: 0 | F97: 0 | G97: 0 | H97: =SUM(C97:G97) -> 0
B98: End of Year — Each Partner's Share | C98: =C95+C96-C97 -> 0 | D98: =D95+D96-D97 -> 0 | E98: =E95+E96-E97 -> 0 | F98: =F95+F96-F97 -> 0 | G98: =G95+G96-G97 -> 0 | H98: =IF(ABS(C94-SUM(C98:G98))<1,TEXT(SUM(C98:G98),"$#,##0")&" ✓",TEXT(SUM(C98:G98),"$#,##0")&" ⚠ gap") -> $0 ✓
B100: NONRECOURSE (§1.752-3 — allocated by Profit %)
B101: Total Partnership Amount (enter full liability) | C101: 0 | D101: (partner shares entered below)
B102: Beginning of Year — Each Partner's Share | C102: ='2021'!C105 -> 0 | D102: ='2021'!D105 -> 0 | E102: ='2021'!E105 -> 0 | F102: ='2021'!F105 -> 0 | G102: ='2021'!G105 -> 0 | H102: =SUM(C102:G102) -> 0
B103: Increases in Share During Year | C103: 0 | D103: 0 | E103: 0 | F103: 0 | G103: 0 | H103: =SUM(C103:G103) -> 0
B104: Decreases in Share During Year | C104: 0 | D104: 0 | E104: 0 | F104: 0 | G104: 0 | H104: =SUM(C104:G104) -> 0
B105: End of Year — Each Partner's Share | C105: =C102+C103-C104 -> 0 | D105: =D102+D103-D104 -> 0 | E105: =E102+E103-E104 -> 0 | F105: =F102+F103-F104 -> 0 | G105: =G102+G103-G104 -> 0 | H105: =IF(ABS(C101-SUM(C105:G105))<1,TEXT(SUM(C105:G105),"$#,##0")&" ✓",TEXT(SUM(C105:G105),"$#,##0")&" ⚠ gap") -> $0 ✓
B107: QNRF (§465(b)(6) — Qualified Nonrecourse Financing)
B108: Total Partnership Amount (enter full liability) | C108: 0 | D108: (partner shares entered below)
B109: Beginning of Year — Each Partner's Share | C109: ='2021'!C112 -> 0 | D109: ='2021'!D112 -> 0 | E109: ='2021'!E112 -> 0 | F109: ='2021'!F112 -> 0 | G109: ='2021'!G112 -> 0 | H109: =SUM(C109:G109) -> 0
...

Sheet 2023
A1: Sample Partnership LLC — Tax Year 2023 (Period 3 of 5)
B2: Blue = inputs. Green = cross-sheet links. Gold = key figures. Update ownership % table (Section A) if interests changed.
B4: SECTION A | OWNERSHIP TABLE — 2023
B5: Nonrecourse liabilities allocated by Profit %. Losses allocated by Loss %. Capital % = economic ownership.
B6: Partner / Metric | C6: ABC Management LLC | D6: Partner A | E6: Partner B | F6: Partner C Trust | G6: Partner D Trust | H6: Check (= 100%?)
B7: Entity Type | C7: General Partner (GP) | D7: Individual | E7: Individual | F7: Trust | G7: Trust
B8: Status | C8: Active | D8: Active | E8: Active | F8: Active | G8: Active
B9: Capital % | C9: 0.2 | D9: 0.2 | E9: 0.2 | F9: 0.2 | G9: 0.2 | H9: =IF(ABS(SUM(C9:G9)-1)<0.0001,TEXT(SUM(C9:G9),"0.0%")&" ✓",TEXT(SUM(C9:G9),"0.0%")&" ⚠") -> 100.0% ✓
B10: Profit % | C10: 0.2 | D10: 0.2 | E10: 0.2 | F10: 0.2 | G10: 0.2 | H10: =IF(ABS(SUM(C10:G10)-1)<0.0001,TEXT(SUM(C10:G10),"0.0%")&" ✓",TEXT(SUM(C10:G10),"0.0%")&" ⚠") -> 100.0% ✓
B11: Loss % | C11: 0.2 | D11: 0.2 | E11: 0.2 | F11: 0.2 | G11: 0.2 | H11: =IF(ABS(SUM(C11:G11)-1)<0.0001,TEXT(SUM(C11:G11),"0.0%")&" ✓",TEXT(SUM(C11:G11),"0.0%")&" ⚠") -> 100.0% ✓
B13: SECTION B | TAX BASIS WORKSHEET — IRC §705 / Rev. Proc. 2020-13 — 2023
B14: K-1 box refs in each label. Lines 4 & 7 auto-linked from Section D. §704(d): losses suspended when decreases exceed basis.
B15: Line Item (K-1 Box Reference) | C15: ABC Management LLC | D15: Partner A | E15: Partner B | F15: Partner C Trust | G15: Partner D Trust | H15: Total
B17: 1. Basis at Beginning of Year | C17: ='2022'!C59 -> 0 | D17: ='2022'!D59 -> 0 | E17: ='2022'!E59 -> 0 | F17: ='2022'!F59 -> 0 | G17: ='2022'!G59 -> 0 | H17: =SUM(C17:G17) -> 0
B18: INCREASES (Lines 2–4)
B19: 2a. Cash contributions | C19: 0 | D19: 0 | E19: 0 | F19: 0 | G19: 0 | H19: =SUM(C19:G19) -> 0
B20: 2b. Property contributions (adjusted tax basis, not FMV) | C20: 0 | D20: 0 | E20: 0 | F20: 0 | G20: 0 | H20: =SUM(C20:G20) -> 0
B21: Line 3 — Distributive Share of Income / Gain (K-1)
B22: 3a. Ordinary business income (Box 1) | C22: 0 | D22: 0 | E22: 0 | F22: 0 | G22: 0 | H22: =SUM(C22:G22) -> 0
B23: 3b. Rental real estate / other net rental income (Boxes 2–3) | C23: 0 | D23: 0 | E23: 0 | F23: 0 | G23: 0 | H23: =SUM(C23:G23) -> 0
B24: 3c. Guaranteed payments — services & capital (Boxes 4a, 4b) | C24: 0 | D24: 0 | E24: 0 | F24: 0 | G24: 0 | H24: =SUM(C24:G24) -> 0
B25: 3d. Interest, dividends, royalties (Boxes 5, 6a–6c, 7) | C25: 0 | D25: 0 | E25: 0 | F25: 0 | G25: 0 | H25: =SUM(C25:G25) -> 0
B26: 3e. Net short-term capital gain (Box 8) | C26: 0 | D26: 0 | E26: 0 | F26: 0 | G26: 0 | H26: =SUM(C26:G26) -> 0
B27: 3f. Net long-term / §1250 / collectibles gain (Boxes 9a–9c) | C27: 0 | D27: 0 | E27: 0 | F27: 0 | G27: 0 | H27: =SUM(C27:G27) -> 0
B28: 3g. Net §1231 gain (Box 10) | C28: 0 | D28: 0 | E28: 0 | F28: 0 | G28: 0 | H28: =SUM(C28:G28) -> 0
B29: 3h. Other income & gain (Box 11) | C29: 0 | D29: 0 | E29: 0 | F29: 0 | G29: 0 | H29: =SUM(C29:G29) -> 0
B30: 3i. Tax-exempt income (Box 18, Code A) | C30: 0 | D30: 0 | E30: 0 | F30: 0 | G30: 0 | H30: =SUM(C30:G30) -> 0
B31: 3j. Excess depletion & other increases (Box 20T; other) | C31: 0 | D31: 0 | E31: 0 | F31: 0 | G31: 0 | H31: =SUM(C31:G31) -> 0
B32: Line 3 Total — Income / Gain Subtotal | C32: =SUM(C22:C31) -> 0 | D32: =SUM(D22:D31) -> 0 | E32: =SUM(E22:E31) -> 0 | F32: =SUM(F22:F31) -> 0 | G32: =SUM(G22:G31) -> 0 | H32: =SUM(C32:G32) -> 0
B33: Line 4 — §752 Liability Increase ← auto-linked from Section D
B34: 4. Net increase in share of partnership liabilities (§752) | C34: =MAX(0,C117) -> 0 | D34: =MAX(0,D117) -> 0 | E34: =MAX(0,E117) -> 0 | F34: =MAX(0,F117) -> 0 | G34: =MAX(0,G117) -> 0 | H34: =SUM(C34:G34) -> 0
B35: TOTAL INCREASES (2a + 2b + Line 3 + Line 4) | C35: =C19+C20+C32+C34 -> 0 | D35: =D19+D20+D32+D34 -> 0 | E35: =E19+E20+E32+E34 -> 0 | F35: =F19+F20+F32+F34 -> 0 | G35: =G19+G20+G32+G34 -> 0 | H35: =SUM(C35:G35) -> 0
B36: DECREASES (Lines 5–7)
B37: 5a. Cash distributions (Box 19, Code A) | C37: 0 | D37: 0 | E37: 0 | F37: 0 | G37: 0 | H37: =SUM(C37:G37) -> 0
B38: 5b. Property distributions (adjusted tax basis) (Box 19, Code B) | C38: 0 | D38: 0 | E38: 0 | F38: 0 | G38: 0 | H38: =SUM(C38:G38) -> 0
B39: Line 6 — Distributive Share of Deductions / Losses (K-1)
B40: 6a. Ordinary business loss (Box 1) | C40: 0 | D40: 0 | E40: 0 | F40: 0 | G40: 0 | H40: =SUM(C40:G40) -> 0
B41: 6b. Rental real estate / other net rental loss (Boxes 2–3) | C41: 0 | D41: 0 | E41: 0 | F41: 0 | G41: 0 | H41: =SUM(C41:G41) -> 0
B42: 6c. Net short-term capital loss (Box 8) | C42: 0 | D42: 0 | E42: 0 | F42: 0 | G42: 0 | H42: =SUM(C42:G42) -> 0
B43: 6d. Net long-term capital loss (Box 9a) | C43: 0 | D43: 0 | E43: 0 | F43: 0 | G43: 0 | H43: =SUM(C43:G43) -> 0
B44: 6e. Net §1231 loss (Box 10) | C44: 0 | D44: 0 | E44: 0 | F44: 0 | G44: 0 | H44: =SUM(C44:G44) -> 0
B45: 6f. Section 179 deduction (Box 12) | C45: 0 | D45: 0 | E45: 0 | F45: 0 | G45: 0 | H45: =SUM(C45:G45) -> 0
B46: 6g. Charitable contributions (Box 13A) | C46: 0 | D46: 0 | E46: 0 | F46: 0 | G46: 0 | H46: =SUM(C46:G46) -> 0
B47: 6h. Investment interest / §59(e)(2) / excess biz interest (Box 13 B/C/K) | C47: 0 | D47: 0 | E47: 0 | F47: 0 | G47: 0 | H47: =SUM(C47:G47) -> 0
B48: 6i. Foreign taxes paid or accrued (Box 13L) | C48: 0 | D48: 0 | E48: 0 | F48: 0 | G48: 0 | H48: =SUM(C48:G48) -> 0
B49: 6j. Nondeductible / non-capitalizable expenses (Box 18C) | C49: 0 | D49: 0 | E49: 0 | F49: 0 | G49: 0 | H49: =SUM(C49:G49) -> 0
B50: 6k. Other losses & deductions (Box 11 / Box 13W / Box 20T; other) | C50: 0 | D50: 0 | E50: 0 | F50: 0 | G50: 0 | H50: =SUM(C50:G50) -> 0
B51: Line 6 Total — Deductions / Losses Subtotal | C51: =SUM(C40:C50) -> 0 | D51: =SUM(D40:D50) -> 0 | E51: =SUM(E40:E50) -> 0 | F51: =SUM(F40:F50) -> 0 | G51: =SUM(G40:G50) -> 0 | H51: =SUM(C51:G51) -> 0
B52: Line 7 — §752 Liability Decrease ← auto-linked from Section D
B53: 7. Net decrease in share of partnership liabilities (§752) | C53: =MAX(0,-C117) -> 0 | D53: =MAX(0,-D117) -> 0 | E53: =MAX(0,-E117) -> 0 | F53: =MAX(0,-F117) -> 0 | G53: =MAX(0,-G117) -> 0 | H53: =SUM(C53:G53) -> 0
B54: TOTAL DECREASES (5a + 5b + Line 6 + Line 7) | C54: =C37+C38+C51+C53 -> 0 | D54: =D37+D38+D51+D53 -> 0 | E54: =E37+E38+E51+E53 -> 0 | F54: =F37+F38+F51+F53 -> 0 | G54: =G37+G38+G51+G53 -> 0 | H54: =SUM(C54:G54) -> 0
B55: §704(d) LOSS LIMITATION
B56: 8. Pre-Limitation Adjusted Basis (Line 1 + Increases − Decreases) | C56: =C17+C35-C54 -> 0 | D56: =D17+D35-D54 -> 0 | E56: =E17+E35-E54 -> 0 | F56: =F17+F35-F54 -> 0 | G56: =G17+G35-G54 -> 0 | H56: =SUM(C56:G56) -> 0
B57: 9a. §704(d) Suspended Losses [excess of decreases over available basis] | C57: =MAX(0,-C56) -> 0 | D57: =MAX(0,-D56) -> 0 | E57: =MAX(0,-E56) -> 0 | F57: =MAX(0,-F56) -> 0 | G57: =MAX(0,-G56) -> 0 | H57: =SUM(C57:G57) -> 0
B58: 9b. Prior-Year §704(d) Suspended Losses Restored ← auto from 2022 | C58: =MIN('2022'!C57,MAX(0,C56)) -> 0 | D58: =MIN('2022'!D57,MAX(0,D56)) -> 0 | E58: =MIN('2022'!E57,MAX(0,E56)) -> 0 | F58: =MIN('2022'!F57,MAX(0,F56)) -> 0 | G58: =MIN('2022'!G57,MAX(0,G56)) -> 0 | H58: =SUM(C58:G58) -> 0
B59: 10. Ending Tax Basis — December 31, 2023 | C59: =MAX(0,C56)-C58 -> 0 | D59: =MAX(0,D56)-D58 -> 0 | E59: =MAX(0,E56)-E58 -> 0 | F59: =MAX(0,F56)-F58 -> 0 | G59: =MAX(0,G56)-G58 -> 0 | H59: =SUM(C59:G59) -> 0
B61: SECTION C | AT-RISK BASIS — IRC §465 — 2023
B62: At-risk = cash/property + recourse debt + QNRF. Nonrecourse does NOT increase at-risk. §465 applied after §704(d).
B63: Line Item | C63: ABC Management LLC | D63: Partner A | E63: Partner B | F63: Partner C Trust | G63: Partner D Trust | H63: Total
B65: 1. At-Risk Amount at Beginning of Year | C65: ='2022'!C86 -> 0 | D65: ='2022'!D86 -> 0 | E65: ='2022'!E86 -> 0 | F65: ='2022'!F86 -> 0 | G65: ='2022'!G86 -> 0 | H65: =SUM(C65:G65) -> 0
B66: INCREASES
B67: 2a. Cash contributions ← Section B Line 2a | C67: =C19 -> 0 | D67: =D19 -> 0 | E67: =E19 -> 0 | F67: =F19 -> 0 | G67: =G19 -> 0 | H67: =SUM(C67:G67) -> 0
B68: 2b. Property contributions ← Section B Line 2b | C68: =C20 -> 0 | D68: =D20 -> 0 | E68: =E20 -> 0 | F68: =F20 -> 0 | G68: =G20 -> 0 | H68: =SUM(C68:G68) -> 0
B69: 2c. Recourse borrowings ← Section D Recourse increases | C69: =C96 -> 0 | D69: =D96 -> 0 | E69: =E96 -> 0 | F69: =F96 -> 0 | G69: =G96 -> 0 | H69: =SUM(C69:G69) -> 0
B70: 2d. QNRF increase ← Section D | C70: =MAX(0,C112-'2022'!C112) -> 0 | D70: =MAX(0,D112-'2022'!D112) -> 0 | E70: =MAX(0,E112-'2022'!E112) -> 0 | F70: =MAX(0,F112-'2022'!F112) -> 0 | G70: =MAX(0,G112-'2022'!G112) -> 0 | H70: =SUM(C70:G70) -> 0
B71: 2e. Distributive share of income/gain ← Section B Line 3 | C71: =C32 -> 0 | D71: =D32 -> 0 | E71: =E32 -> 0 | F71: =F32 -> 0 | G71: =G32 -> 0 | H71: =SUM(C71:G71) -> 0
B72: 2f. Other increases to at-risk amount | C72: 0 | D72: 0 | E72: 0 | F72: 0 | G72: 0 | H72: =SUM(C72:G72) -> 0
B73: TOTAL INCREASES | C73: =C67+C68+C69+C70+C71+C72 -> 0 | D73: =D67+D68+D69+D70+D71+D72 -> 0 | E73: =E67+E68+E69+E70+E71+E72 -> 0 | F73: =F67+F68+F69+F70+F71+F72 -> 0 | G73: =G67+G68+G69+G70+G71+G72 -> 0 | H73: =SUM(C73:G73) -> 0
B74: DECREASES
B75: 3a. Cash distributions ← Section B Line 5a | C75: =C37 -> 0 | D75: =D37 -> 0 | E75: =E37 -> 0 | F75: =F37 -> 0 | G75: =G37 -> 0 | H75: =SUM(C75:G75) -> 0
B76: 3b. Property distributions ← Section B Line 5b | C76: =C38 -> 0 | D76: =D38 -> 0 | E76: =E38 -> 0 | F76: =F38 -> 0 | G76: =G38 -> 0 | H76: =SUM(C76:G76) -> 0
B77: 3c. Recourse repayments ← Section D Recourse decreases | C77: =C97 -> 0 | D77: =D97 -> 0 | E77: =E97 -> 0 | F77: =F97 -> 0 | G77: =G97 -> 0 | H77: =SUM(C77:G77) -> 0
B78: 3d. QNRF decrease ← Section D | C78: =MAX(0,'2022'!C112-C112) -> 0 | D78: =MAX(0,'2022'!D112-D112) -> 0 | E78: =MAX(0,'2022'!E112-E112) -> 0 | F78: =MAX(0,'2022'!F112-F112) -> 0 | G78: =MAX(0,'2022'!G112-G112) -> 0 | H78: =SUM(C78:G78) -> 0
B79: 3e. Distributive share of deductions/losses ← Section B Line 6 | C79: =C51 -> 0 | D79: =D51 -> 0 | E79: =E51 -> 0 | F79: =F51 -> 0 | G79: =G51 -> 0 | H79: =SUM(C79:G79) -> 0
B80: 3f. Other decreases to at-risk amount | C80: 0 | D80: 0 | E80: 0 | F80: 0 | G80: 0 | H80: =SUM(C80:G80) -> 0
B81: TOTAL DECREASES | C81: =C75+C76+C77+C78+C79+C80 -> 0 | D81: =D75+D76+D77+D78+D79+D80 -> 0 | E81: =E75+E76+E77+E78+E79+E80 -> 0 | F81: =F75+F76+F77+F78+F79+F80 -> 0 | G81: =G75+G76+G77+G78+G79+G80 -> 0 | H81: =SUM(C81:G81) -> 0
B82: 4. Pre-Limitation At-Risk Amount | C82: =C65+C73-C81 -> 0 | D82: =D65+D73-D81 -> 0 | E82: =E65+E73-E81 -> 0 | F82: =F65+F73-F81 -> 0 | G82: =G65+G73-G81 -> 0 | H82: =SUM(C82:G82) -> 0
B83: §465 LOSS LIMITATION
B84: 5a. §465 Suspended Losses | C84: =MAX(0,-C82) -> 0 | D84: =MAX(0,-D82) -> 0 | E84: =MAX(0,-E82) -> 0 | F84: =MAX(0,-F82) -> 0 | G84: =MAX(0,-G82) -> 0 | H84: =SUM(C84:G84) -> 0
B85: 5b. Prior-Year §465 Suspended Losses Restored ← auto from 2022 | C85: =MIN('2022'!C84,MAX(0,C82)) -> 0 | D85: =MIN('2022'!D84,MAX(0,D82)) -> 0 | E85: =MIN('2022'!E84,MAX(0,E82)) -> 0 | F85: =MIN('2022'!F84,MAX(0,F82)) -> 0 | G85: =MIN('2022'!G84,MAX(0,G82)) -> 0 | H85: =SUM(C85:G85) -> 0
B86: 6. Ending At-Risk Amount — December 31, 2023 | C86: =MAX(0,C82)-C85 -> 0 | D86: =MAX(0,D82)-D85 -> 0 | E86: =MAX(0,E82)-E85 -> 0 | F86: =MAX(0,F82)-F85 -> 0 | G86: =MAX(0,G82)-G85 -> 0 | H86: =SUM(C86:G86) -> 0
B87: 7. Effective Loss Limit (lesser of Tax Basis & At-Risk) | C87: =MIN(C59,C86) -> 0 | D87: =MIN(D59,D86) -> 0 | E87: =MIN(E59,E86) -> 0 | F87: =MIN(F59,F86) -> 0 | G87: =MIN(G59,G86) -> 0 | H87: =SUM(C87:G87) -> 0
B89: SECTION D | LIABILITY SCHEDULE — IRC §752 — 2023
B90: Recourse §1.752-2: economic risk of loss. Nonrecourse §1.752-3: allocated by Profit %. QNRF §465(b)(6): real property.
B91: Item | C91: ABC Management LLC | D91: Partner A | E91: Partner B | F91: Partner C Trust | G91: Partner D Trust | H91: Total / Sum Check
B93: RECOURSE (§1.752-2 — Economic Risk of Loss)
B94: Total Partnership Amount (enter full liability) | C94: 0 | D94: (partner shares entered below)
B95: Beginning of Year — Each Partner's Share | C95: ='2022'!C98 -> 0 | D95: ='2022'!D98 -> 0 | E95: ='2022'!E98 -> 0 | F95: ='2022'!F98 -> 0 | G95: ='2022'!G98 -> 0 | H95: =SUM(C95:G95) -> 0
B96: Increases in Share During Year | C96: 0 | D96: 0 | E96: 0 | F96: 0 | G96: 0 | H96: =SUM(C96:G96) -> 0
B97: Decreases in Share During Year | C97: 0 | D97: 0 | E97: 0 | F97: 0 | G97: 0 | H97: =SUM(C97:G97) -> 0
B98: End of Year — Each Partner's Share | C98: =C95+C96-C97 -> 0 | D98: =D95+D96-D97 -> 0 | E98: =E95+E96-E97 -> 0 | F98: =F95+F96-F97 -> 0 | G98: =G95+G96-G97 -> 0 | H98: =IF(ABS(C94-SUM(C98:G98))<1,TEXT(SUM(C98:G98),"$#,##0")&" ✓",TEXT(SUM(C98:G98),"$#,##0")&" ⚠ gap") -> $0 ✓
B100: NONRECOURSE (§1.752-3 — allocated by Profit %)
B101: Total Partnership Amount (enter full liability) | C101: 0 | D101: (partner shares entered below)
B102: Beginning of Year — Each Partner's Share | C102: ='2022'!C105 -> 0 | D102: ='2022'!D105 -> 0 | E102: ='2022'!E105 -> 0 | F102: ='2022'!F105 -> 0 | G102: ='2022'!G105 -> 0 | H102: =SUM(C102:G102) -> 0
B103: Increases in Share During Year | C103: 0 | D103: 0 | E103: 0 | F103: 0 | G103: 0 | H103: =SUM(C103:G103) -> 0
B104: Decreases in Share During Year | C104: 0 | D104: 0 | E104: 0 | F104: 0 | G104: 0 | H104: =SUM(C104:G104) -> 0
B105: End of Year — Each Partner's Share | C105: =C102+C103-C104 -> 0 | D105: =D102+D103-D104 -> 0 | E105: =E102+E103-E104 -> 0 | F105: =F102+F103-F104 -> 0 | G105: =G102+G103-G104 -> 0 | H105: =IF(ABS(C101-SUM(C105:G105))<1,TEXT(SUM(C105:G105),"$#,##0")&" ✓",TEXT(SUM(C105:G105),"$#,##0")&" ⚠ gap") -> $0 ✓
B107: QNRF (§465(b)(6) — Qualified Nonrecourse Financing)
B108: Total Partnership Amount (enter full liability) | C108: 0 | D108: (partner shares entered below)
B109: Beginning of Year — Each Partner's Share | C109: ='2022'!C112 -> 0 | D109: ='2022'!D112 -> 0 | E109: ='2022'!E112 -> 0 | F109: ='2022'!F112 -> 0 | G109: ='2022'!G112 -> 0 | H109: =SUM(C109:G109) -> 0
...

Sheet 2024
A1: Sample Partnership LLC — Tax Year 2024 (Period 4 of 5)
B2: Blue = inputs. Green = cross-sheet links. Gold = key figures. Update ownership % table (Section A) if interests changed.
B4: SECTION A | OWNERSHIP TABLE — 2024
B5: Nonrecourse liabilities allocated by Profit %. Losses allocated by Loss %. Capital % = economic ownership.
B6: Partner / Metric | C6: ABC Management LLC | D6: Partner A | E6: Partner B | F6: Partner C Trust | G6: Partner D Trust | H6: Check (= 100%?)
B7: Entity Type | C7: General Partner (GP) | D7: Individual | E7: Individual | F7: Trust | G7: Trust
B8: Status | C8: Active | D8: Active | E8: Active | F8: Active | G8: Active
B9: Capital % | C9: 0.2 | D9: 0.2 | E9: 0.2 | F9: 0.2 | G9: 0.2 | H9: =IF(ABS(SUM(C9:G9)-1)<0.0001,TEXT(SUM(C9:G9),"0.0%")&" ✓",TEXT(SUM(C9:G9),"0.0%")&" ⚠") -> 100.0% ✓
B10: Profit % | C10: 0.2 | D10: 0.2 | E10: 0.2 | F10: 0.2 | G10: 0.2 | H10: =IF(ABS(SUM(C10:G10)-1)<0.0001,TEXT(SUM(C10:G10),"0.0%")&" ✓",TEXT(SUM(C10:G10),"0.0%")&" ⚠") -> 100.0% ✓
B11: Loss % | C11: 0.2 | D11: 0.2 | E11: 0.2 | F11: 0.2 | G11: 0.2 | H11: =IF(ABS(SUM(C11:G11)-1)<0.0001,TEXT(SUM(C11:G11),"0.0%")&" ✓",TEXT(SUM(C11:G11),"0.0%")&" ⚠") -> 100.0% ✓
B13: SECTION B | TAX BASIS WORKSHEET — IRC §705 / Rev. Proc. 2020-13 — 2024
B14: K-1 box refs in each label. Lines 4 & 7 auto-linked from Section D. §704(d): losses suspended when decreases exceed basis.
B15: Line Item (K-1 Box Reference) | C15: ABC Management LLC | D15: Partner A | E15: Partner B | F15: Partner C Trust | G15: Partner D Trust | H15: Total
B17: 1. Basis at Beginning of Year | C17: ='2023'!C59 -> 0 | D17: ='2023'!D59 -> 0 | E17: ='2023'!E59 -> 0 | F17: ='2023'!F59 -> 0 | G17: ='2023'!G59 -> 0 | H17: =SUM(C17:G17) -> 0
B18: INCREASES (Lines 2–4)
B19: 2a. Cash contributions | C19: 0 | D19: 0 | E19: 0 | F19: 0 | G19: 0 | H19: =SUM(C19:G19) -> 0
B20: 2b. Property contributions (adjusted tax basis, not FMV) | C20: 0 | D20: 0 | E20: 0 | F20: 0 | G20: 0 | H20: =SUM(C20:G20) -> 0
B21: Line 3 — Distributive Share of Income / Gain (K-1)
B22: 3a. Ordinary business income (Box 1) | C22: 0 | D22: 0 | E22: 0 | F22: 0 | G22: 0 | H22: =SUM(C22:G22) -> 0
B23: 3b. Rental real estate / other net rental income (Boxes 2–3) | C23: 0 | D23: 0 | E23: 0 | F23: 0 | G23: 0 | H23: =SUM(C23:G23) -> 0
B24: 3c. Guaranteed payments — services & capital (Boxes 4a, 4b) | C24: 0 | D24: 0 | E24: 0 | F24: 0 | G24: 0 | H24: =SUM(C24:G24) -> 0
B25: 3d. Interest, dividends, royalties (Boxes 5, 6a–6c, 7) | C25: 0 | D25: 0 | E25: 0 | F25: 0 | G25: 0 | H25: =SUM(C25:G25) -> 0
B26: 3e. Net short-term capital gain (Box 8) | C26: 0 | D26: 0 | E26: 0 | F26: 0 | G26: 0 | H26: =SUM(C26:G26) -> 0
B27: 3f. Net long-term / §1250 / collectibles gain (Boxes 9a–9c) | C27: 0 | D27: 0 | E27: 0 | F27: 0 | G27: 0 | H27: =SUM(C27:G27) -> 0
B28: 3g. Net §1231 gain (Box 10) | C28: 0 | D28: 0 | E28: 0 | F28: 0 | G28: 0 | H28: =SUM(C28:G28) -> 0
B29: 3h. Other income & gain (Box 11) | C29: 0 | D29: 0 | E29: 0 | F29: 0 | G29: 0 | H29: =SUM(C29:G29) -> 0
B30: 3i. Tax-exempt income (Box 18, Code A) | C30: 0 | D30: 0 | E30: 0 | F30: 0 | G30: 0 | H30: =SUM(C30:G30) -> 0
B31: 3j. Excess depletion & other increases (Box 20T; other) | C31: 0 | D31: 0 | E31: 0 | F31: 0 | G31: 0 | H31: =SUM(C31:G31) -> 0
B32: Line 3 Total — Income / Gain Subtotal | C32: =SUM(C22:C31) -> 0 | D32: =SUM(D22:D31) -> 0 | E32: =SUM(E22:E31) -> 0 | F32: =SUM(F22:F31) -> 0 | G32: =SUM(G22:G31) -> 0 | H32: =SUM(C32:G32) -> 0
B33: Line 4 — §752 Liability Increase ← auto-linked from Section D
B34: 4. Net increase in share of partnership liabilities (§752) | C34: =MAX(0,C117) -> 0 | D34: =MAX(0,D117) -> 0 | E34: =MAX(0,E117) -> 0 | F34: =MAX(0,F117) -> 0 | G34: =MAX(0,G117) -> 0 | H34: =SUM(C34:G34) -> 0
B35: TOTAL INCREASES (2a + 2b + Line 3 + Line 4) | C35: =C19+C20+C32+C34 -> 0 | D35: =D19+D20+D32+D34 -> 0 | E35: =E19+E20+E32+E34 -> 0 | F35: =F19+F20+F32+F34 -> 0 | G35: =G19+G20+G32+G34 -> 0 | H35: =SUM(C35:G35) -> 0
B36: DECREASES (Lines 5–7)
B37: 5a. Cash distributions (Box 19, Code A) | C37: 0 | D37: 0 | E37: 0 | F37: 0 | G37: 0 | H37: =SUM(C37:G37) -> 0
B38: 5b. Property distributions (adjusted tax basis) (Box 19, Code B) | C38: 0 | D38: 0 | E38: 0 | F38: 0 | G38: 0 | H38: =SUM(C38:G38) -> 0
B39: Line 6 — Distributive Share of Deductions / Losses (K-1)
B40: 6a. Ordinary business loss (Box 1) | C40: 0 | D40: 0 | E40: 0 | F40: 0 | G40: 0 | H40: =SUM(C40:G40) -> 0
B41: 6b. Rental real estate / other net rental loss (Boxes 2–3) | C41: 0 | D41: 0 | E41: 0 | F41: 0 | G41: 0 | H41: =SUM(C41:G41) -> 0
B42: 6c. Net short-term capital loss (Box 8) | C42: 0 | D42: 0 | E42: 0 | F42: 0 | G42: 0 | H42: =SUM(C42:G42) -> 0
B43: 6d. Net long-term capital loss (Box 9a) | C43: 0 | D43: 0 | E43: 0 | F43: 0 | G43: 0 | H43: =SUM(C43:G43) -> 0
B44: 6e. Net §1231 loss (Box 10) | C44: 0 | D44: 0 | E44: 0 | F44: 0 | G44: 0 | H44: =SUM(C44:G44) -> 0
B45: 6f. Section 179 deduction (Box 12) | C45: 0 | D45: 0 | E45: 0 | F45: 0 | G45: 0 | H45: =SUM(C45:G45) -> 0
B46: 6g. Charitable contributions (Box 13A) | C46: 0 | D46: 0 | E46: 0 | F46: 0 | G46: 0 | H46: =SUM(C46:G46) -> 0
B47: 6h. Investment interest / §59(e)(2) / excess biz interest (Box 13 B/C/K) | C47: 0 | D47: 0 | E47: 0 | F47: 0 | G47: 0 | H47: =SUM(C47:G47) -> 0
B48: 6i. Foreign taxes paid or accrued (Box 13L) | C48: 0 | D48: 0 | E48: 0 | F48: 0 | G48: 0 | H48: =SUM(C48:G48) -> 0
B49: 6j. Nondeductible / non-capitalizable expenses (Box 18C) | C49: 0 | D49: 0 | E49: 0 | F49: 0 | G49: 0 | H49: =SUM(C49:G49) -> 0
B50: 6k. Other losses & deductions (Box 11 / Box 13W / Box 20T; other) | C50: 0 | D50: 0 | E50: 0 | F50: 0 | G50: 0 | H50: =SUM(C50:G50) -> 0
B51: Line 6 Total — Deductions / Losses Subtotal | C51: =SUM(C40:C50) -> 0 | D51: =SUM(D40:D50) -> 0 | E51: =SUM(E40:E50) -> 0 | F51: =SUM(F40:F50) -> 0 | G51: =SUM(G40:G50) -> 0 | H51: =SUM(C51:G51) -> 0
B52: Line 7 — §752 Liability Decrease ← auto-linked from Section D
B53: 7. Net decrease in share of partnership liabilities (§752) | C53: =MAX(0,-C117) -> 0 | D53: =MAX(0,-D117) -> 0 | E53: =MAX(0,-E117) -> 0 | F53: =MAX(0,-F117) -> 0 | G53: =MAX(0,-G117) -> 0 | H53: =SUM(C53:G53) -> 0
B54: TOTAL DECREASES (5a + 5b + Line 6 + Line 7) | C54: =C37+C38+C51+C53 -> 0 | D54: =D37+D38+D51+D53 -> 0 | E54: =E37+E38+E51+E53 -> 0 | F54: =F37+F38+F51+F53 -> 0 | G54: =G37+G38+G51+G53 -> 0 | H54: =SUM(C54:G54) -> 0
B55: §704(d) LOSS LIMITATION
B56: 8. Pre-Limitation Adjusted Basis (Line 1 + Increases − Decreases) | C56: =C17+C35-C54 -> 0 | D56: =D17+D35-D54 -> 0 | E56: =E17+E35-E54 -> 0 | F56: =F17+F35-F54 -> 0 | G56: =G17+G35-G54 -> 0 | H56: =SUM(C56:G56) -> 0
B57: 9a. §704(d) Suspended Losses [excess of decreases over available basis] | C57: =MAX(0,-C56) -> 0 | D57: =MAX(0,-D56) -> 0 | E57: =MAX(0,-E56) -> 0 | F57: =MAX(0,-F56) -> 0 | G57: =MAX(0,-G56) -> 0 | H57: =SUM(C57:G57) -> 0
B58: 9b. Prior-Year §704(d) Suspended Losses Restored ← auto from 2023 | C58: =MIN('2023'!C57,MAX(0,C56)) -> 0 | D58: =MIN('2023'!D57,MAX(0,D56)) -> 0 | E58: =MIN('2023'!E57,MAX(0,E56)) -> 0 | F58: =MIN('2023'!F57,MAX(0,F56)) -> 0 | G58: =MIN('2023'!G57,MAX(0,G56)) -> 0 | H58: =SUM(C58:G58) -> 0
B59: 10. Ending Tax Basis — December 31, 2024 | C59: =MAX(0,C56)-C58 -> 0 | D59: =MAX(0,D56)-D58 -> 0 | E59: =MAX(0,E56)-E58 -> 0 | F59: =MAX(0,F56)-F58 -> 0 | G59: =MAX(0,G56)-G58 -> 0 | H59: =SUM(C59:G59) -> 0
B61: SECTION C | AT-RISK BASIS — IRC §465 — 2024
B62: At-risk = cash/property + recourse debt + QNRF. Nonrecourse does NOT increase at-risk. §465 applied after §704(d).
B63: Line Item | C63: ABC Management LLC | D63: Partner A | E63: Partner B | F63: Partner C Trust | G63: Partner D Trust | H63: Total
B65: 1. At-Risk Amount at Beginning of Year | C65: ='2023'!C86 -> 0 | D65: ='2023'!D86 -> 0 | E65: ='2023'!E86 -> 0 | F65: ='2023'!F86 -> 0 | G65: ='2023'!G86 -> 0 | H65: =SUM(C65:G65) -> 0
B66: INCREASES
B67: 2a. Cash contributions ← Section B Line 2a | C67: =C19 -> 0 | D67: =D19 -> 0 | E67: =E19 -> 0 | F67: =F19 -> 0 | G67: =G19 -> 0 | H67: =SUM(C67:G67) -> 0
B68: 2b. Property contributions ← Section B Line 2b | C68: =C20 -> 0 | D68: =D20 -> 0 | E68: =E20 -> 0 | F68: =F20 -> 0 | G68: =G20 -> 0 | H68: =SUM(C68:G68) -> 0
B69: 2c. Recourse borrowings ← Section D Recourse increases | C69: =C96 -> 0 | D69: =D96 -> 0 | E69: =E96 -> 0 | F69: =F96 -> 0 | G69: =G96 -> 0 | H69: =SUM(C69:G69) -> 0
B70: 2d. QNRF increase ← Section D | C70: =MAX(0,C112-'2023'!C112) -> 0 | D70: =MAX(0,D112-'2023'!D112) -> 0 | E70: =MAX(0,E112-'2023'!E112) -> 0 | F70: =MAX(0,F112-'2023'!F112) -> 0 | G70: =MAX(0,G112-'2023'!G112) -> 0 | H70: =SUM(C70:G70) -> 0
B71: 2e. Distributive share of income/gain ← Section B Line 3 | C71: =C32 -> 0 | D71: =D32 -> 0 | E71: =E32 -> 0 | F71: =F32 -> 0 | G71: =G32 -> 0 | H71: =SUM(C71:G71) -> 0
B72: 2f. Other increases to at-risk amount | C72: 0 | D72: 0 | E72: 0 | F72: 0 | G72: 0 | H72: =SUM(C72:G72) -> 0
B73: TOTAL INCREASES | C73: =C67+C68+C69+C70+C71+C72 -> 0 | D73: =D67+D68+D69+D70+D71+D72 -> 0 | E73: =E67+E68+E69+E70+E71+E72 -> 0 | F73: =F67+F68+F69+F70+F71+F72 -> 0 | G73: =G67+G68+G69+G70+G71+G72 -> 0 | H73: =SUM(C73:G73) -> 0
B74: DECREASES
B75: 3a. Cash distributions ← Section B Line 5a | C75: =C37 -> 0 | D75: =D37 -> 0 | E75: =E37 -> 0 | F75: =F37 -> 0 | G75: =G37 -> 0 | H75: =SUM(C75:G75) -> 0
B76: 3b. Property distributions ← Section B Line 5b | C76: =C38 -> 0 | D76: =D38 -> 0 | E76: =E38 -> 0 | F76: =F38 -> 0 | G76: =G38 -> 0 | H76: =SUM(C76:G76) -> 0
B77: 3c. Recourse repayments ← Section D Recourse decreases | C77: =C97 -> 0 | D77: =D97 -> 0 | E77: =E97 -> 0 | F77: =F97 -> 0 | G77: =G97 -> 0 | H77: =SUM(C77:G77) -> 0
B78: 3d. QNRF decrease ← Section D | C78: =MAX(0,'2023'!C112-C112) -> 0 | D78: =MAX(0,'2023'!D112-D112) -> 0 | E78: =MAX(0,'2023'!E112-E112) -> 0 | F78: =MAX(0,'2023'!F112-F112) -> 0 | G78: =MAX(0,'2023'!G112-G112) -> 0 | H78: =SUM(C78:G78) -> 0
B79: 3e. Distributive share of deductions/losses ← Section B Line 6 | C79: =C51 -> 0 | D79: =D51 -> 0 | E79: =E51 -> 0 | F79: =F51 -> 0 | G79: =G51 -> 0 | H79: =SUM(C79:G79) -> 0
B80: 3f. Other decreases to at-risk amount | C80: 0 | D80: 0 | E80: 0 | F80: 0 | G80: 0 | H80: =SUM(C80:G80) -> 0
B81: TOTAL DECREASES | C81: =C75+C76+C77+C78+C79+C80 -> 0 | D81: =D75+D76+D77+D78+D79+D80 -> 0 | E81: =E75+E76+E77+E78+E79+E80 -> 0 | F81: =F75+F76+F77+F78+F79+F80 -> 0 | G81: =G75+G76+G77+G78+G79+G80 -> 0 | H81: =SUM(C81:G81) -> 0
B82: 4. Pre-Limitation At-Risk Amount | C82: =C65+C73-C81 -> 0 | D82: =D65+D73-D81 -> 0 | E82: =E65+E73-E81 -> 0 | F82: =F65+F73-F81 -> 0 | G82: =G65+G73-G81 -> 0 | H82: =SUM(C82:G82) -> 0
B83: §465 LOSS LIMITATION
B84: 5a. §465 Suspended Losses | C84: =MAX(0,-C82) -> 0 | D84: =MAX(0,-D82) -> 0 | E84: =MAX(0,-E82) -> 0 | F84: =MAX(0,-F82) -> 0 | G84: =MAX(0,-G82) -> 0 | H84: =SUM(C84:G84) -> 0
B85: 5b. Prior-Year §465 Suspended Losses Restored ← auto from 2023 | C85: =MIN('2023'!C84,MAX(0,C82)) -> 0 | D85: =MIN('2023'!D84,MAX(0,D82)) -> 0 | E85: =MIN('2023'!E84,MAX(0,E82)) -> 0 | F85: =MIN('2023'!F84,MAX(0,F82)) -> 0 | G85: =MIN('2023'!G84,MAX(0,G82)) -> 0 | H85: =SUM(C85:G85) -> 0
B86: 6. Ending At-Risk Amount — December 31, 2024 | C86: =MAX(0,C82)-C85 -> 0 | D86: =MAX(0,D82)-D85 -> 0 | E86: =MAX(0,E82)-E85 -> 0 | F86: =MAX(0,F82)-F85 -> 0 | G86: =MAX(0,G82)-G85 -> 0 | H86: =SUM(C86:G86) -> 0
B87: 7. Effective Loss Limit (lesser of Tax Basis & At-Risk) | C87: =MIN(C59,C86) -> 0 | D87: =MIN(D59,D86) -> 0 | E87: =MIN(E59,E86) -> 0 | F87: =MIN(F59,F86) -> 0 | G87: =MIN(G59,G86) -> 0 | H87: =SUM(C87:G87) -> 0
B89: SECTION D | LIABILITY SCHEDULE — IRC §752 — 2024
B90: Recourse §1.752-2: economic risk of loss. Nonrecourse §1.752-3: allocated by Profit %. QNRF §465(b)(6): real property.
B91: Item | C91: ABC Management LLC | D91: Partner A | E91: Partner B | F91: Partner C Trust | G91: Partner D Trust | H91: Total / Sum Check
B93: RECOURSE (§1.752-2 — Economic Risk of Loss)
B94: Total Partnership Amount (enter full liability) | C94: 0 | D94: (partner shares entered below)
B95: Beginning of Year — Each Partner's Share | C95: ='2023'!C98 -> 0 | D95: ='2023'!D98 -> 0 | E95: ='2023'!E98 -> 0 | F95: ='2023'!F98 -> 0 | G95: ='2023'!G98 -> 0 | H95: =SUM(C95:G95) -> 0
B96: Increases in Share During Year | C96: 0 | D96: 0 | E96: 0 | F96: 0 | G96: 0 | H96: =SUM(C96:G96) -> 0
B97: Decreases in Share During Year | C97: 0 | D97: 0 | E97: 0 | F97: 0 | G97: 0 | H97: =SUM(C97:G97) -> 0
B98: End of Year — Each Partner's Share | C98: =C95+C96-C97 -> 0 | D98: =D95+D96-D97 -> 0 | E98: =E95+E96-E97 -> 0 | F98: =F95+F96-F97 -> 0 | G98: =G95+G96-G97 -> 0 | H98: =IF(ABS(C94-SUM(C98:G98))<1,TEXT(SUM(C98:G98),"$#,##0")&" ✓",TEXT(SUM(C98:G98),"$#,##0")&" ⚠ gap") -> $0 ✓
B100: NONRECOURSE (§1.752-3 — allocated by Profit %)
B101: Total Partnership Amount (enter full liability) | C101: 0 | D101: (partner shares entered below)
B102: Beginning of Year — Each Partner's Share | C102: ='2023'!C105 -> 0 | D102: ='2023'!D105 -> 0 | E102: ='2023'!E105 -> 0 | F102: ='2023'!F105 -> 0 | G102: ='2023'!G105 -> 0 | H102: =SUM(C102:G102) -> 0
B103: Increases in Share During Year | C103: 0 | D103: 0 | E103: 0 | F103: 0 | G103: 0 | H103: =SUM(C103:G103) -> 0
B104: Decreases in Share During Year | C104: 0 | D104: 0 | E104: 0 | F104: 0 | G104: 0 | H104: =SUM(C104:G104) -> 0
B105: End of Year — Each Partner's Share | C105: =C102+C103-C104 -> 0 | D105: =D102+D103-D104 -> 0 | E105: =E102+E103-E104 -> 0 | F105: =F102+F103-F104 -> 0 | G105: =G102+G103-G104 -> 0 | H105: =IF(ABS(C101-SUM(C105:G105))<1,TEXT(SUM(C105:G105),"$#,##0")&" ✓",TEXT(SUM(C105:G105),"$#,##0")&" ⚠ gap") -> $0 ✓
B107: QNRF (§465(b)(6) — Qualified Nonrecourse Financing)
B108: Total Partnership Amount (enter full liability) | C108: 0 | D108: (partner shares entered below)
B109: Beginning of Year — Each Partner's Share | C109: ='2023'!C112 -> 0 | D109: ='2023'!D112 -> 0 | E109: ='2023'!E112 -> 0 | F109: ='2023'!F112 -> 0 | G109: ='2023'!G112 -> 0 | H109: =SUM(C109:G109) -> 0
...

Sheet 2025
A1: Sample Partnership LLC — Tax Year 2025 (Period 5 of 5)
B2: Blue = inputs. Green = cross-sheet links. Gold = key figures. Update ownership % table (Section A) if interests changed.
B4: SECTION A | OWNERSHIP TABLE — 2025
B5: Nonrecourse liabilities allocated by Profit %. Losses allocated by Loss %. Capital % = economic ownership.
B6: Partner / Metric | C6: ABC Management LLC | D6: Partner A | E6: Partner B | F6: Partner C Trust | G6: Partner D Trust | H6: Check (= 100%?)
B7: Entity Type | C7: General Partner (GP) | D7: Individual | E7: Individual | F7: Trust | G7: Trust
B8: Status | C8: Active | D8: Active | E8: Active | F8: Active | G8: Active
B9: Capital % | C9: 0.2 | D9: 0.2 | E9: 0.2 | F9: 0.2 | G9: 0.2 | H9: =IF(ABS(SUM(C9:G9)-1)<0.0001,TEXT(SUM(C9:G9),"0.0%")&" ✓",TEXT(SUM(C9:G9),"0.0%")&" ⚠") -> 100.0% ✓
B10: Profit % | C10: 0.2 | D10: 0.2 | E10: 0.2 | F10: 0.2 | G10: 0.2 | H10: =IF(ABS(SUM(C10:G10)-1)<0.0001,TEXT(SUM(C10:G10),"0.0%")&" ✓",TEXT(SUM(C10:G10),"0.0%")&" ⚠") -> 100.0% ✓
B11: Loss % | C11: 0.2 | D11: 0.2 | E11: 0.2 | F11: 0.2 | G11: 0.2 | H11: =IF(ABS(SUM(C11:G11)-1)<0.0001,TEXT(SUM(C11:G11),"0.0%")&" ✓",TEXT(SUM(C11:G11),"0.0%")&" ⚠") -> 100.0% ✓
B13: SECTION B | TAX BASIS WORKSHEET — IRC §705 / Rev. Proc. 2020-13 — 2025
B14: K-1 box refs in each label. Lines 4 & 7 auto-linked from Section D. §704(d): losses suspended when decreases exceed basis.
B15: Line Item (K-1 Box Reference) | C15: ABC Management LLC | D15: Partner A | E15: Partner B | F15: Partner C Trust | G15: Partner D Trust | H15: Total
B17: 1. Basis at Beginning of Year | C17: ='2024'!C59 -> 0 | D17: ='2024'!D59 -> 0 | E17: ='2024'!E59 -> 0 | F17: ='2024'!F59 -> 0 | G17: ='2024'!G59 -> 0 | H17: =SUM(C17:G17) -> 0
B18: INCREASES (Lines 2–4)
B19: 2a. Cash contributions | C19: 0 | D19: 0 | E19: 0 | F19: 0 | G19: 0 | H19: =SUM(C19:G19) -> 0
B20: 2b. Property contributions (adjusted tax basis, not FMV) | C20: 0 | D20: 0 | E20: 0 | F20: 0 | G20: 0 | H20: =SUM(C20:G20) -> 0
B21: Line 3 — Distributive Share of Income / Gain (K-1)
B22: 3a. Ordinary business income (Box 1) | C22: 0 | D22: 0 | E22: 0 | F22: 0 | G22: 0 | H22: =SUM(C22:G22) -> 0
B23: 3b. Rental real estate / other net rental income (Boxes 2–3) | C23: 0 | D23: 0 | E23: 0 | F23: 0 | G23: 0 | H23: =SUM(C23:G23) -> 0
B24: 3c. Guaranteed payments — services & capital (Boxes 4a, 4b) | C24: 0 | D24: 0 | E24: 0 | F24: 0 | G24: 0 | H24: =SUM(C24:G24) -> 0
B25: 3d. Interest, dividends, royalties (Boxes 5, 6a–6c, 7) | C25: 0 | D25: 0 | E25: 0 | F25: 0 | G25: 0 | H25: =SUM(C25:G25) -> 0
B26: 3e. Net short-term capital gain (Box 8) | C26: 0 | D26: 0 | E26: 0 | F26: 0 | G26: 0 | H26: =SUM(C26:G26) -> 0
B27: 3f. Net long-term / §1250 / collectibles gain (Boxes 9a–9c) | C27: 0 | D27: 0 | E27: 0 | F27: 0 | G27: 0 | H27: =SUM(C27:G27) -> 0
B28: 3g. Net §1231 gain (Box 10) | C28: 0 | D28: 0 | E28: 0 | F28: 0 | G28: 0 | H28: =SUM(C28:G28) -> 0
B29: 3h. Other income & gain (Box 11) | C29: 0 | D29: 0 | E29: 0 | F29: 0 | G29: 0 | H29: =SUM(C29:G29) -> 0
B30: 3i. Tax-exempt income (Box 18, Code A) | C30: 0 | D30: 0 | E30: 0 | F30: 0 | G30: 0 | H30: =SUM(C30:G30) -> 0
B31: 3j. Excess depletion & other increases (Box 20T; other) | C31: 0 | D31: 0 | E31: 0 | F31: 0 | G31: 0 | H31: =SUM(C31:G31) -> 0
B32: Line 3 Total — Income / Gain Subtotal | C32: =SUM(C22:C31) -> 0 | D32: =SUM(D22:D31) -> 0 | E32: =SUM(E22:E31) -> 0 | F32: =SUM(F22:F31) -> 0 | G32: =SUM(G22:G31) -> 0 | H32: =SUM(C32:G32) -> 0
B33: Line 4 — §752 Liability Increase ← auto-linked from Section D
B34: 4. Net increase in share of partnership liabilities (§752) | C34: =MAX(0,C117) -> 0 | D34: =MAX(0,D117) -> 0 | E34: =MAX(0,E117) -> 0 | F34: =MAX(0,F117) -> 0 | G34: =MAX(0,G117) -> 0 | H34: =SUM(C34:G34) -> 0
B35: TOTAL INCREASES (2a + 2b + Line 3 + Line 4) | C35: =C19+C20+C32+C34 -> 0 | D35: =D19+D20+D32+D34 -> 0 | E35: =E19+E20+E32+E34 -> 0 | F35: =F19+F20+F32+F34 -> 0 | G35: =G19+G20+G32+G34 -> 0 | H35: =SUM(C35:G35) -> 0
B36: DECREASES (Lines 5–7)
B37: 5a. Cash distributions (Box 19, Code A) | C37: 0 | D37: 0 | E37: 0 | F37: 0 | G37: 0 | H37: =SUM(C37:G37) -> 0
B38: 5b. Property distributions (adjusted tax basis) (Box 19, Code B) | C38: 0 | D38: 0 | E38: 0 | F38: 0 | G38: 0 | H38: =SUM(C38:G38) -> 0
B39: Line 6 — Distributive Share of Deductions / Losses (K-1)
B40: 6a. Ordinary business loss (Box 1) | C40: 0 | D40: 0 | E40: 0 | F40: 0 | G40: 0 | H40: =SUM(C40:G40) -> 0
B41: 6b. Rental real estate / other net rental loss (Boxes 2–3) | C41: 0 | D41: 0 | E41: 0 | F41: 0 | G41: 0 | H41: =SUM(C41:G41) -> 0
B42: 6c. Net short-term capital loss (Box 8) | C42: 0 | D42: 0 | E42: 0 | F42: 0 | G42: 0 | H42: =SUM(C42:G42) -> 0
B43: 6d. Net long-term capital loss (Box 9a) | C43: 0 | D43: 0 | E43: 0 | F43: 0 | G43: 0 | H43: =SUM(C43:G43) -> 0
B44: 6e. Net §1231 loss (Box 10) | C44: 0 | D44: 0 | E44: 0 | F44: 0 | G44: 0 | H44: =SUM(C44:G44) -> 0
B45: 6f. Section 179 deduction (Box 12) | C45: 0 | D45: 0 | E45: 0 | F45: 0 | G45: 0 | H45: =SUM(C45:G45) -> 0
B46: 6g. Charitable contributions (Box 13A) | C46: 0 | D46: 0 | E46: 0 | F46: 0 | G46: 0 | H46: =SUM(C46:G46) -> 0
B47: 6h. Investment interest / §59(e)(2) / excess biz interest (Box 13 B/C/K) | C47: 0 | D47: 0 | E47: 0 | F47: 0 | G47: 0 | H47: =SUM(C47:G47) -> 0
B48: 6i. Foreign taxes paid or accrued (Box 13L) | C48: 0 | D48: 0 | E48: 0 | F48: 0 | G48: 0 | H48: =SUM(C48:G48) -> 0
B49: 6j. Nondeductible / non-capitalizable expenses (Box 18C) | C49: 0 | D49: 0 | E49: 0 | F49: 0 | G49: 0 | H49: =SUM(C49:G49) -> 0
B50: 6k. Other losses & deductions (Box 11 / Box 13W / Box 20T; other) | C50: 0 | D50: 0 | E50: 0 | F50: 0 | G50: 0 | H50: =SUM(C50:G50) -> 0
B51: Line 6 Total — Deductions / Losses Subtotal | C51: =SUM(C40:C50) -> 0 | D51: =SUM(D40:D50) -> 0 | E51: =SUM(E40:E50) -> 0 | F51: =SUM(F40:F50) -> 0 | G51: =SUM(G40:G50) -> 0 | H51: =SUM(C51:G51) -> 0
B52: Line 7 — §752 Liability Decrease ← auto-linked from Section D
B53: 7. Net decrease in share of partnership liabilities (§752) | C53: =MAX(0,-C117) -> 0 | D53: =MAX(0,-D117) -> 0 | E53: =MAX(0,-E117) -> 0 | F53: =MAX(0,-F117) -> 0 | G53: =MAX(0,-G117) -> 0 | H53: =SUM(C53:G53) -> 0
B54: TOTAL DECREASES (5a + 5b + Line 6 + Line 7) | C54: =C37+C38+C51+C53 -> 0 | D54: =D37+D38+D51+D53 -> 0 | E54: =E37+E38+E51+E53 -> 0 | F54: =F37+F38+F51+F53 -> 0 | G54: =G37+G38+G51+G53 -> 0 | H54: =SUM(C54:G54) -> 0
B55: §704(d) LOSS LIMITATION
B56: 8. Pre-Limitation Adjusted Basis (Line 1 + Increases − Decreases) | C56: =C17+C35-C54 -> 0 | D56: =D17+D35-D54 -> 0 | E56: =E17+E35-E54 -> 0 | F56: =F17+F35-F54 -> 0 | G56: =G17+G35-G54 -> 0 | H56: =SUM(C56:G56) -> 0
B57: 9a. §704(d) Suspended Losses [excess of decreases over available basis] | C57: =MAX(0,-C56) -> 0 | D57: =MAX(0,-D56) -> 0 | E57: =MAX(0,-E56) -> 0 | F57: =MAX(0,-F56) -> 0 | G57: =MAX(0,-G56) -> 0 | H57: =SUM(C57:G57) -> 0
B58: 9b. Prior-Year §704(d) Suspended Losses Restored ← auto from 2024 | C58: =MIN('2024'!C57,MAX(0,C56)) -> 0 | D58: =MIN('2024'!D57,MAX(0,D56)) -> 0 | E58: =MIN('2024'!E57,MAX(0,E56)) -> 0 | F58: =MIN('2024'!F57,MAX(0,F56)) -> 0 | G58: =MIN('2024'!G57,MAX(0,G56)) -> 0 | H58: =SUM(C58:G58) -> 0
B59: 10. Ending Tax Basis — December 31, 2025 | C59: =MAX(0,C56)-C58 -> 0 | D59: =MAX(0,D56)-D58 -> 0 | E59: =MAX(0,E56)-E58 -> 0 | F59: =MAX(0,F56)-F58 -> 0 | G59: =MAX(0,G56)-G58 -> 0 | H59: =SUM(C59:G59) -> 0
B61: SECTION C | AT-RISK BASIS — IRC §465 — 2025
B62: At-risk = cash/property + recourse debt + QNRF. Nonrecourse does NOT increase at-risk. §465 applied after §704(d).
B63: Line Item | C63: ABC Management LLC | D63: Partner A | E63: Partner B | F63: Partner C Trust | G63: Partner D Trust | H63: Total
B65: 1. At-Risk Amount at Beginning of Year | C65: ='2024'!C86 -> 0 | D65: ='2024'!D86 -> 0 | E65: ='2024'!E86 -> 0 | F65: ='2024'!F86 -> 0 | G65: ='2024'!G86 -> 0 | H65: =SUM(C65:G65) -> 0
B66: INCREASES
B67: 2a. Cash contributions ← Section B Line 2a | C67: =C19 -> 0 | D67: =D19 -> 0 | E67: =E19 -> 0 | F67: =F19 -> 0 | G67: =G19 -> 0 | H67: =SUM(C67:G67) -> 0
B68: 2b. Property contributions ← Section B Line 2b | C68: =C20 -> 0 | D68: =D20 -> 0 | E68: =E20 -> 0 | F68: =F20 -> 0 | G68: =G20 -> 0 | H68: =SUM(C68:G68) -> 0
B69: 2c. Recourse borrowings ← Section D Recourse increases | C69: =C96 -> 0 | D69: =D96 -> 0 | E69: =E96 -> 0 | F69: =F96 -> 0 | G69: =G96 -> 0 | H69: =SUM(C69:G69) -> 0
B70: 2d. QNRF increase ← Section D | C70: =MAX(0,C112-'2024'!C112) -> 0 | D70: =MAX(0,D112-'2024'!D112) -> 0 | E70: =MAX(0,E112-'2024'!E112) -> 0 | F70: =MAX(0,F112-'2024'!F112) -> 0 | G70: =MAX(0,G112-'2024'!G112) -> 0 | H70: =SUM(C70:G70) -> 0
B71: 2e. Distributive share of income/gain ← Section B Line 3 | C71: =C32 -> 0 | D71: =D32 -> 0 | E71: =E32 -> 0 | F71: =F32 -> 0 | G71: =G32 -> 0 | H71: =SUM(C71:G71) -> 0
B72: 2f. Other increases to at-risk amount | C72: 0 | D72: 0 | E72: 0 | F72: 0 | G72: 0 | H72: =SUM(C72:G72) -> 0
B73: TOTAL INCREASES | C73: =C67+C68+C69+C70+C71+C72 -> 0 | D73: =D67+D68+D69+D70+D71+D72 -> 0 | E73: =E67+E68+E69+E70+E71+E72 -> 0 | F73: =F67+F68+F69+F70+F71+F72 -> 0 | G73: =G67+G68+G69+G70+G71+G72 -> 0 | H73: =SUM(C73:G73) -> 0
B74: DECREASES
B75: 3a. Cash distributions ← Section B Line 5a | C75: =C37 -> 0 | D75: =D37 -> 0 | E75: =E37 -> 0 | F75: =F37 -> 0 | G75: =G37 -> 0 | H75: =SUM(C75:G75) -> 0
B76: 3b. Property distributions ← Section B Line 5b | C76: =C38 -> 0 | D76: =D38 -> 0 | E76: =E38 -> 0 | F76: =F38 -> 0 | G76: =G38 -> 0 | H76: =SUM(C76:G76) -> 0
B77: 3c. Recourse repayments ← Section D Recourse decreases | C77: =C97 -> 0 | D77: =D97 -> 0 | E77: =E97 -> 0 | F77: =F97 -> 0 | G77: =G97 -> 0 | H77: =SUM(C77:G77) -> 0
B78: 3d. QNRF decrease ← Section D | C78: =MAX(0,'2024'!C112-C112) -> 0 | D78: =MAX(0,'2024'!D112-D112) -> 0 | E78: =MAX(0,'2024'!E112-E112) -> 0 | F78: =MAX(0,'2024'!F112-F112) -> 0 | G78: =MAX(0,'2024'!G112-G112) -> 0 | H78: =SUM(C78:G78) -> 0
B79: 3e. Distributive share of deductions/losses ← Section B Line 6 | C79: =C51 -> 0 | D79: =D51 -> 0 | E79: =E51 -> 0 | F79: =F51 -> 0 | G79: =G51 -> 0 | H79: =SUM(C79:G79) -> 0
B80: 3f. Other decreases to at-risk amount | C80: 0 | D80: 0 | E80: 0 | F80: 0 | G80: 0 | H80: =SUM(C80:G80) -> 0
B81: TOTAL DECREASES | C81: =C75+C76+C77+C78+C79+C80 -> 0 | D81: =D75+D76+D77+D78+D79+D80 -> 0 | E81: =E75+E76+E77+E78+E79+E80 -> 0 | F81: =F75+F76+F77+F78+F79+F80 -> 0 | G81: =G75+G76+G77+G78+G79+G80 -> 0 | H81: =SUM(C81:G81) -> 0
B82: 4. Pre-Limitation At-Risk Amount | C82: =C65+C73-C81 -> 0 | D82: =D65+D73-D81 -> 0 | E82: =E65+E73-E81 -> 0 | F82: =F65+F73-F81 -> 0 | G82: =G65+G73-G81 -> 0 | H82: =SUM(C82:G82) -> 0
B83: §465 LOSS LIMITATION
B84: 5a. §465 Suspended Losses | C84: =MAX(0,-C82) -> 0 | D84: =MAX(0,-D82) -> 0 | E84: =MAX(0,-E82) -> 0 | F84: =MAX(0,-F82) -> 0 | G84: =MAX(0,-G82) -> 0 | H84: =SUM(C84:G84) -> 0
B85: 5b. Prior-Year §465 Suspended Losses Restored ← auto from 2024 | C85: =MIN('2024'!C84,MAX(0,C82)) -> 0 | D85: =MIN('2024'!D84,MAX(0,D82)) -> 0 | E85: =MIN('2024'!E84,MAX(0,E82)) -> 0 | F85: =MIN('2024'!F84,MAX(0,F82)) -> 0 | G85: =MIN('2024'!G84,MAX(0,G82)) -> 0 | H85: =SUM(C85:G85) -> 0
B86: 6. Ending At-Risk Amount — December 31, 2025 | C86: =MAX(0,C82)-C85 -> 0 | D86: =MAX(0,D82)-D85 -> 0 | E86: =MAX(0,E82)-E85 -> 0 | F86: =MAX(0,F82)-F85 -> 0 | G86: =MAX(0,G82)-G85 -> 0 | H86: =SUM(C86:G86) -> 0
B87: 7. Effective Loss Limit (lesser of Tax Basis & At-Risk) | C87: =MIN(C59,C86) -> 0 | D87: =MIN(D59,D86) -> 0 | E87: =MIN(E59,E86) -> 0 | F87: =MIN(F59,F86) -> 0 | G87: =MIN(G59,G86) -> 0 | H87: =SUM(C87:G87) -> 0
B89: SECTION D | LIABILITY SCHEDULE — IRC §752 — 2025
B90: Recourse §1.752-2: economic risk of loss. Nonrecourse §1.752-3: allocated by Profit %. QNRF §465(b)(6): real property.
B91: Item | C91: ABC Management LLC | D91: Partner A | E91: Partner B | F91: Partner C Trust | G91: Partner D Trust | H91: Total / Sum Check
B93: RECOURSE (§1.752-2 — Economic Risk of Loss)
B94: Total Partnership Amount (enter full liability) | C94: 0 | D94: (partner shares entered below)
B95: Beginning of Year — Each Partner's Share | C95: ='2024'!C98 -> 0 | D95: ='2024'!D98 -> 0 | E95: ='2024'!E98 -> 0 | F95: ='2024'!F98 -> 0 | G95: ='2024'!G98 -> 0 | H95: =SUM(C95:G95) -> 0
B96: Increases in Share During Year | C96: 0 | D96: 0 | E96: 0 | F96: 0 | G96: 0 | H96: =SUM(C96:G96) -> 0
B97: Decreases in Share During Year | C97: 0 | D97: 0 | E97: 0 | F97: 0 | G97: 0 | H97: =SUM(C97:G97) -> 0
B98: End of Year — Each Partner's Share | C98: =C95+C96-C97 -> 0 | D98: =D95+D96-D97 -> 0 | E98: =E95+E96-E97 -> 0 | F98: =F95+F96-F97 -> 0 | G98: =G95+G96-G97 -> 0 | H98: =IF(ABS(C94-SUM(C98:G98))<1,TEXT(SUM(C98:G98),"$#,##0")&" ✓",TEXT(SUM(C98:G98),"$#,##0")&" ⚠ gap") -> $0 ✓
B100: NONRECOURSE (§1.752-3 — allocated by Profit %)
B101: Total Partnership Amount (enter full liability) | C101: 0 | D101: (partner shares entered below)
B102: Beginning of Year — Each Partner's Share | C102: ='2024'!C105 -> 0 | D102: ='2024'!D105 -> 0 | E102: ='2024'!E105 -> 0 | F102: ='2024'!F105 -> 0 | G102: ='2024'!G105 -> 0 | H102: =SUM(C102:G102) -> 0
B103: Increases in Share During Year | C103: 0 | D103: 0 | E103: 0 | F103: 0 | G103: 0 | H103: =SUM(C103:G103) -> 0
B104: Decreases in Share During Year | C104: 0 | D104: 0 | E104: 0 | F104: 0 | G104: 0 | H104: =SUM(C104:G104) -> 0
B105: End of Year — Each Partner's Share | C105: =C102+C103-C104 -> 0 | D105: =D102+D103-D104 -> 0 | E105: =E102+E103-E104 -> 0 | F105: =F102+F103-F104 -> 0 | G105: =G102+G103-G104 -> 0 | H105: =IF(ABS(C101-SUM(C105:G105))<1,TEXT(SUM(C105:G105),"$#,##0")&" ✓",TEXT(SUM(C105:G105),"$#,##0")&" ⚠ gap") -> $0 ✓
B107: QNRF (§465(b)(6) — Qualified Nonrecourse Financing)
B108: Total Partnership Amount (enter full liability) | C108: 0 | D108: (partner shares entered below)
B109: Beginning of Year — Each Partner's Share | C109: ='2024'!C112 -> 0 | D109: ='2024'!D112 -> 0 | E109: ='2024'!E112 -> 0 | F109: ='2024'!F112 -> 0 | G109: ='2024'!G112 -> 0 | H109: =SUM(C109:G109) -> 0
...

Sheet Summary
A1: Sample Partnership LLC — Summary Dashboard | 2021–2025
B2: Auto-populated from each year tab.
B4: Metric | C4: ABC Management LLC | D4: Partner A | E4: Partner B | F4: Partner C Trust | G4: Partner D Trust | H4: Total
B6: 2021 — Period 1 of 5
B7: Ending Tax Basis (§705, Line 10) | C7: ='2021'!C59 -> 0 | D7: ='2021'!D59 -> 0 | E7: ='2021'!E59 -> 0 | F7: ='2021'!F59 -> 0 | G7: ='2021'!G59 -> 0 | H7: =SUM(C7:G7) -> 0
B8: Ending At-Risk (§465, Line 6) | C8: ='2021'!C86 -> 0 | D8: ='2021'!D86 -> 0 | E8: ='2021'!E86 -> 0 | F8: ='2021'!F86 -> 0 | G8: ='2021'!G86 -> 0 | H8: =SUM(C8:G8) -> 0
B9: Effective Loss Limit (MIN of Basis & At-Risk) | C9: =MIN('2021'!C59,'2021'!C86) -> 0 | D9: =MIN('2021'!D59,'2021'!D86) -> 0 | E9: =MIN('2021'!E59,'2021'!E86) -> 0 | F9: =MIN('2021'!F59,'2021'!F86) -> 0 | G9: =MIN('2021'!G59,'2021'!G86) -> 0 | H9: =SUM(C9:G9) -> 0
B10: Net §752 Liability Change | C10: ='2021'!C117 -> 0 | D10: ='2021'!D117 -> 0 | E10: ='2021'!E117 -> 0 | F10: ='2021'!F117 -> 0 | G10: ='2021'!G117 -> 0 | H10: =SUM(C10:G10) -> 0
B11: Capital % | C11: ='2021'!C9 -> 0.2 | D11: ='2021'!D9 -> 0.2 | E11: ='2021'!E9 -> 0.2 | F11: ='2021'!F9 -> 0.2 | G11: ='2021'!G9 -> 0.2 | H11: =SUM(C11:G11) -> 1
B13: 2022 — Period 2 of 5
B14: Ending Tax Basis (§705, Line 10) | C14: ='2022'!C59 -> 0 | D14: ='2022'!D59 -> 0 | E14: ='2022'!E59 -> 0 | F14: ='2022'!F59 -> 0 | G14: ='2022'!G59 -> 0 | H14: =SUM(C14:G14) -> 0
B15: Ending At-Risk (§465, Line 6) | C15: ='2022'!C86 -> 0 | D15: ='2022'!D86 -> 0 | E15: ='2022'!E86 -> 0 | F15: ='2022'!F86 -> 0 | G15: ='2022'!G86 -> 0 | H15: =SUM(C15:G15) -> 0
B16: Effective Loss Limit (MIN of Basis & At-Risk) | C16: =MIN('2022'!C59,'2022'!C86) -> 0 | D16: =MIN('2022'!D59,'2022'!D86) -> 0 | E16: =MIN('2022'!E59,'2022'!E86) -> 0 | F16: =MIN('2022'!F59,'2022'!F86) -> 0 | G16: =MIN('2022'!G59,'2022'!G86) -> 0 | H16: =SUM(C16:G16) -> 0
B17: Net §752 Liability Change | C17: ='2022'!C117 -> 0 | D17: ='2022'!D117 -> 0 | E17: ='2022'!E117 -> 0 | F17: ='2022'!F117 -> 0 | G17: ='2022'!G117 -> 0 | H17: =SUM(C17:G17) -> 0
B18: Capital % | C18: ='2022'!C9 -> 0.2 | D18: ='2022'!D9 -> 0.2 | E18: ='2022'!E9 -> 0.2 | F18: ='2022'!F9 -> 0.2 | G18: ='2022'!G9 -> 0.2 | H18: =SUM(C18:G18) -> 1
B20: 2023 — Period 3 of 5
B21: Ending Tax Basis (§705, Line 10) | C21: ='2023'!C59 -> 0 | D21: ='2023'!D59 -> 0 | E21: ='2023'!E59 -> 0 | F21: ='2023'!F59 -> 0 | G21: ='2023'!G59 -> 0 | H21: =SUM(C21:G21) -> 0
B22: Ending At-Risk (§465, Line 6) | C22: ='2023'!C86 -> 0 | D22: ='2023'!D86 -> 0 | E22: ='2023'!E86 -> 0 | F22: ='2023'!F86 -> 0 | G22: ='2023'!G86 -> 0 | H22: =SUM(C22:G22) -> 0
B23: Effective Loss Limit (MIN of Basis & At-Risk) | C23: =MIN('2023'!C59,'2023'!C86) -> 0 | D23: =MIN('2023'!D59,'2023'!D86) -> 0 | E23: =MIN('2023'!E59,'2023'!E86) -> 0 | F23: =MIN('2023'!F59,'2023'!F86) -> 0 | G23: =MIN('2023'!G59,'2023'!G86) -> 0 | H23: =SUM(C23:G23) -> 0
B24: Net §752 Liability Change | C24: ='2023'!C117 -> 0 | D24: ='2023'!D117 -> 0 | E24: ='2023'!E117 -> 0 | F24: ='2023'!F117 -> 0 | G24: ='2023'!G117 -> 0 | H24: =SUM(C24:G24) -> 0
B25: Capital % | C25: ='2023'!C9 -> 0.2 | D25: ='2023'!D9 -> 0.2 | E25: ='2023'!E9 -> 0.2 | F25: ='2023'!F9 -> 0.2 | G25: ='2023'!G9 -> 0.2 | H25: =SUM(C25:G25) -> 1
B27: 2024 — Period 4 of 5
B28: Ending Tax Basis (§705, Line 10) | C28: ='2024'!C59 -> 0 | D28: ='2024'!D59 -> 0 | E28: ='2024'!E59 -> 0 | F28: ='2024'!F59 -> 0 | G28: ='2024'!G59 -> 0 | H28: =SUM(C28:G28) -> 0
B29: Ending At-Risk (§465, Line 6) | C29: ='2024'!C86 -> 0 | D29: ='2024'!D86 -> 0 | E29: ='2024'!E86 -> 0 | F29: ='2024'!F86 -> 0 | G29: ='2024'!G86 -> 0 | H29: =SUM(C29:G29) -> 0
B30: Effective Loss Limit (MIN of Basis & At-Risk) | C30: =MIN('2024'!C59,'2024'!C86) -> 0 | D30: =MIN('2024'!D59,'2024'!D86) -> 0 | E30: =MIN('2024'!E59,'2024'!E86) -> 0 | F30: =MIN('2024'!F59,'2024'!F86) -> 0 | G30: =MIN('2024'!G59,'2024'!G86) -> 0 | H30: =SUM(C30:G30) -> 0
B31: Net §752 Liability Change | C31: ='2024'!C117 -> 0 | D31: ='2024'!D117 -> 0 | E31: ='2024'!E117 -> 0 | F31: ='2024'!F117 -> 0 | G31: ='2024'!G117 -> 0 | H31: =SUM(C31:G31) -> 0
B32: Capital % | C32: ='2024'!C9 -> 0.2 | D32: ='2024'!D9 -> 0.2 | E32: ='2024'!E9 -> 0.2 | F32: ='2024'!F9 -> 0.2 | G32: ='2024'!G9 -> 0.2 | H32: =SUM(C32:G32) -> 1
B34: 2025 — Period 5 of 5
B35: Ending Tax Basis (§705, Line 10) | C35: ='2025'!C59 -> 0 | D35: ='2025'!D59 -> 0 | E35: ='2025'!E59 -> 0 | F35: ='2025'!F59 -> 0 | G35: ='2025'!G59 -> 0 | H35: =SUM(C35:G35) -> 0
B36: Ending At-Risk (§465, Line 6) | C36: ='2025'!C86 -> 0 | D36: ='2025'!D86 -> 0 | E36: ='2025'!E86 -> 0 | F36: ='2025'!F86 -> 0 | G36: ='2025'!G86 -> 0 | H36: =SUM(C36:G36) -> 0
B37: Effective Loss Limit (MIN of Basis & At-Risk) | C37: =MIN('2025'!C59,'2025'!C86) -> 0 | D37: =MIN('2025'!D59,'2025'!D86) -> 0 | E37: =MIN('2025'!E59,'2025'!E86) -> 0 | F37: =MIN('2025'!F59,'2025'!F86) -> 0 | G37: =MIN('2025'!G59,'2025'!G86) -> 0 | H37: =SUM(C37:G37) -> 0
B38: Net §752 Liability Change | C38: ='2025'!C117 -> 0 | D38: ='2025'!D117 -> 0 | E38: ='2025'!E117 -> 0 | F38: ='2025'!F117 -> 0 | G38: ='2025'!G117 -> 0 | H38: =SUM(C38:G38) -> 0
B39: Capital % | C39: ='2025'!C9 -> 0.2 | D39: ='2025'!D9 -> 0.2 | E39: ='2025'!E9 -> 0.2 | F39: ='2025'!F9 -> 0.2 | G39: ='2025'!G9 -> 0.2 | H39: =SUM(C39:G39) -> 1
B41: DISCLAIMER: Template only — not tax advice. Verify all K-1 allocations before entry. Consult a qualified tax advisor.
